{"country":"Latvia","code":"LVA","yearlyData":[{"year":1941,"avgTemp":3.72},{"year":1942,"avgTemp":2.82},{"year":1943,"avgTemp":3.31},{"year":1944,"avgTemp":6.37},{"year":1945,"avgTemp":6.1},{"year":1946,"avgTemp":5.35},{"year":1947,"avgTemp":5.48},{"year":1948,"avgTemp":4.9},{"year":1949,"avgTemp":6.34},{"year":1950,"avgTemp":6.96,"rollingAvg":5.14},{"year":1951,"avgTemp":5.69,"rollingAvg":5.33},{"year":1952,"avgTemp":5.57,"rollingAvg":5.61},{"year":1953,"avgTemp":4.88,"rollingAvg":5.76},{"year":1954,"avgTemp":5.84,"rollingAvg":5.71},{"year":1955,"avgTemp":5.17,"rollingAvg":5.62},{"year":1956,"avgTemp":5.01,"rollingAvg":5.58},{"year":1957,"avgTemp":3.85,"rollingAvg":5.42},{"year":1958,"avgTemp":6.26,"rollingAvg":5.56},{"year":1959,"avgTemp":5.11,"rollingAvg":5.43},{"year":1960,"avgTemp":6.34,"rollingAvg":5.37},{"year":1961,"avgTemp":5.51,"rollingAvg":5.35},{"year":1962,"avgTemp":6.89,"rollingAvg":5.49},{"year":1963,"avgTemp":5.04,"rollingAvg":5.5},{"year":1964,"avgTemp":4.72,"rollingAvg":5.39},{"year":1965,"avgTemp":5.52,"rollingAvg":5.43},{"year":1966,"avgTemp":4.72,"rollingAvg":5.4},{"year":1967,"avgTemp":5.05,"rollingAvg":5.52},{"year":1968,"avgTemp":6.09,"rollingAvg":5.5},{"year":1969,"avgTemp":5.16,"rollingAvg":5.5},{"year":1970,"avgTemp":4.1,"rollingAvg":5.28},{"year":1971,"avgTemp":4.78,"rollingAvg":5.21},{"year":1972,"avgTemp":6.14,"rollingAvg":5.13},{"year":1973,"avgTemp":6.24,"rollingAvg":5.25},{"year":1974,"avgTemp":5.96,"rollingAvg":5.38},{"year":1975,"avgTemp":6.48,"rollingAvg":5.47},{"year":1976,"avgTemp":7.45,"rollingAvg":5.75},{"year":1977,"avgTemp":4.27,"rollingAvg":5.67},{"year":1978,"avgTemp":5.37,"rollingAvg":5.6},{"year":1979,"avgTemp":4.56,"rollingAvg":5.54},{"year":1980,"avgTemp":5.24,"rollingAvg":5.65},{"year":1981,"avgTemp":4.72,"rollingAvg":5.64},{"year":1982,"avgTemp":5.78,"rollingAvg":5.61},{"year":1983,"avgTemp":6.11,"rollingAvg":5.59},{"year":1984,"avgTemp":6.94,"rollingAvg":5.69},{"year":1985,"avgTemp":6.21,"rollingAvg":5.67},{"year":1986,"avgTemp":4.29,"rollingAvg":5.35},{"year":1987,"avgTemp":5.55,"rollingAvg":5.48},{"year":1988,"avgTemp":4.05,"rollingAvg":5.35},{"year":1989,"avgTemp":6.26,"rollingAvg":5.51},{"year":1990,"avgTemp":7.67,"rollingAvg":5.76},{"year":1991,"avgTemp":7.41,"rollingAvg":6.03},{"year":1992,"avgTemp":6.7,"rollingAvg":6.12},{"year":1993,"avgTemp":6.91,"rollingAvg":6.2},{"year":1994,"avgTemp":5.7,"rollingAvg":6.08},{"year":1995,"avgTemp":5.98,"rollingAvg":6.05},{"year":1996,"avgTemp":6.59,"rollingAvg":6.28},{"year":1997,"avgTemp":5.02,"rollingAvg":6.23},{"year":1998,"avgTemp":6.26,"rollingAvg":6.45},{"year":1999,"avgTemp":6.01,"rollingAvg":6.43},{"year":2000,"avgTemp":7.13,"rollingAvg":6.37},{"year":2001,"avgTemp":7.52,"rollingAvg":6.38},{"year":2002,"avgTemp":6.53,"rollingAvg":6.37},{"year":2003,"avgTemp":6.96,"rollingAvg":6.37},{"year":2004,"avgTemp":6.3,"rollingAvg":6.43},{"year":2005,"avgTemp":6.31,"rollingAvg":6.46},{"year":2006,"avgTemp":6.27,"rollingAvg":6.43},{"year":2007,"avgTemp":6.98,"rollingAvg":6.63},{"year":2008,"avgTemp":7.22,"rollingAvg":6.72},{"year":2009,"avgTemp":7.66,"rollingAvg":6.89},{"year":2010,"avgTemp":6.44,"rollingAvg":6.82},{"year":2011,"avgTemp":5.59,"rollingAvg":6.63},{"year":2012,"avgTemp":7.17,"rollingAvg":6.69},{"year":2013,"avgTemp":5.99,"rollingAvg":6.59},{"year":2014,"avgTemp":6.86,"rollingAvg":6.65},{"year":2015,"avgTemp":7.25,"rollingAvg":6.74},{"year":2016,"avgTemp":7.7,"rollingAvg":6.89},{"year":2017,"avgTemp":7,"rollingAvg":6.89},{"year":2018,"avgTemp":6.74,"rollingAvg":6.84},{"year":2019,"avgTemp":7.49,"rollingAvg":6.82},{"year":2020,"avgTemp":8.04,"rollingAvg":6.98},{"year":2021,"avgTemp":8.63,"rollingAvg":7.29},{"year":2022,"avgTemp":6.85,"rollingAvg":7.26},{"year":2023,"avgTemp":7.28,"rollingAvg":7.38},{"year":2024,"avgTemp":7.79,"rollingAvg":7.48},{"year":2025,"avgTemp":8.69,"rollingAvg":7.62}],"monthlyComparison":[{"monthLabel":"Apr 2025","month":4,"year":2025,"recentTemp":7.59,"historicAvg":4.69,"diff":2.9},{"monthLabel":"May 2025","month":5,"year":2025,"recentTemp":14.58,"historicAvg":11.36,"diff":3.22},{"monthLabel":"Jun 2025","month":6,"year":2025,"recentTemp":17.2,"historicAvg":15.25,"diff":1.95},{"monthLabel":"Jul 2025","month":7,"year":2025,"recentTemp":19.16,"historicAvg":16.69,"diff":2.47},{"monthLabel":"Aug 2025","month":8,"year":2025,"recentTemp":18.02,"historicAvg":15.77,"diff":2.25},{"monthLabel":"Sep 2025","month":9,"year":2025,"recentTemp":16.02,"historicAvg":11.37,"diff":4.65},{"monthLabel":"Oct 2025","month":10,"year":2025,"recentTemp":8.21,"historicAvg":6.57,"diff":1.64},{"monthLabel":"Nov 2025","month":11,"year":2025,"recentTemp":3.96,"historicAvg":1.3,"diff":2.66},{"monthLabel":"Dec 2025","month":12,"year":2025,"recentTemp":1.4,"historicAvg":-3.03,"diff":4.43},{"monthLabel":"Jan 2026","month":1,"year":2026,"recentTemp":1.6,"historicAvg":-6.03,"diff":7.63},{"monthLabel":"Feb 2026","month":2,"year":2026,"recentTemp":-3.15,"historicAvg":-5.61,"diff":2.46},{"monthLabel":"Mar 2026","month":3,"year":2026,"recentTemp":3.92,"historicAvg":-1.58,"diff":5.5}],"latestMonthStats":{"label":"Mar 2026","value":3.92,"diff":5.5,"rank":2,"total":86,"recordLabel":"Mar 2008","recordValue":4.61},"latestThreeMonthStats":{"label":"Jan–Mar 2026","value":0.79,"diff":5.2,"rank":4,"total":86,"recordLabel":"Jan–Mar 2021","recordValue":2.5},"monthlyAll":[{"year":1941,"month":1,"value":-13.58},{"year":1941,"month":2,"value":-12.63},{"year":1941,"month":3,"value":-5.12},{"year":1941,"month":4,"value":2.71},{"year":1941,"month":5,"value":11.15},{"year":1941,"month":6,"value":15.35},{"year":1941,"month":7,"value":17.97},{"year":1941,"month":8,"value":15.3},{"year":1941,"month":9,"value":11.25},{"year":1941,"month":10,"value":4.86},{"year":1941,"month":11,"value":3.04},{"year":1941,"month":12,"value":-5.63},{"year":1942,"month":1,"value":-14.24},{"year":1942,"month":2,"value":-6.67},{"year":1942,"month":3,"value":-3.51},{"year":1942,"month":4,"value":0.6},{"year":1942,"month":5,"value":7.39},{"year":1942,"month":6,"value":13.03},{"year":1942,"month":7,"value":19.84},{"year":1942,"month":8,"value":16.7},{"year":1942,"month":9,"value":10.11},{"year":1942,"month":10,"value":3.07},{"year":1942,"month":11,"value":-6.19},{"year":1942,"month":12,"value":-6.25},{"year":1943,"month":1,"value":-15.37},{"year":1943,"month":2,"value":-11.18},{"year":1943,"month":3,"value":-9.28},{"year":1943,"month":4,"value":3.12},{"year":1943,"month":5,"value":9.39},{"year":1943,"month":6,"value":12.83},{"year":1943,"month":7,"value":16.15},{"year":1943,"month":8,"value":17.27},{"year":1943,"month":9,"value":12.76},{"year":1943,"month":10,"value":8},{"year":1943,"month":11,"value":-1.09},{"year":1943,"month":12,"value":-2.84},{"year":1944,"month":1,"value":-10.21},{"year":1944,"month":2,"value":-0.52},{"year":1944,"month":3,"value":0.93},{"year":1944,"month":4,"value":6.05},{"year":1944,"month":5,"value":10.1},{"year":1944,"month":6,"value":15.57},{"year":1944,"month":7,"value":16.59},{"year":1944,"month":8,"value":16.44},{"year":1944,"month":9,"value":12.86},{"year":1944,"month":10,"value":8.11},{"year":1944,"month":11,"value":1.06},{"year":1944,"month":12,"value":-0.59},{"year":1945,"month":1,"value":-1.85},{"year":1945,"month":2,"value":-3.95},{"year":1945,"month":3,"value":-2.11},{"year":1945,"month":4,"value":2.31},{"year":1945,"month":5,"value":9.66},{"year":1945,"month":6,"value":13.89},{"year":1945,"month":7,"value":18.23},{"year":1945,"month":8,"value":17.85},{"year":1945,"month":9,"value":12.83},{"year":1945,"month":10,"value":7.02},{"year":1945,"month":11,"value":1.67},{"year":1945,"month":12,"value":-2.33},{"year":1946,"month":1,"value":-6.79},{"year":1946,"month":2,"value":-2.91},{"year":1946,"month":3,"value":-2.11},{"year":1946,"month":4,"value":4.75},{"year":1946,"month":5,"value":9.69},{"year":1946,"month":6,"value":13.81},{"year":1946,"month":7,"value":18.71},{"year":1946,"month":8,"value":17.58},{"year":1946,"month":9,"value":11.3},{"year":1946,"month":10,"value":5.24},{"year":1946,"month":11,"value":0.68},{"year":1946,"month":12,"value":-5.79},{"year":1947,"month":1,"value":-5.49},{"year":1947,"month":2,"value":-5.54},{"year":1947,"month":3,"value":-2.55},{"year":1947,"month":4,"value":5.72},{"year":1947,"month":5,"value":11.28},{"year":1947,"month":6,"value":16.1},{"year":1947,"month":7,"value":18.38},{"year":1947,"month":8,"value":17.2},{"year":1947,"month":9,"value":13.33},{"year":1947,"month":10,"value":3.28},{"year":1947,"month":11,"value":-0.95},{"year":1947,"month":12,"value":-4.96},{"year":1948,"month":1,"value":-9.15},{"year":1948,"month":2,"value":-12.74},{"year":1948,"month":3,"value":-4.02},{"year":1948,"month":4,"value":4.88},{"year":1948,"month":5,"value":11.24},{"year":1948,"month":6,"value":16.72},{"year":1948,"month":7,"value":17.9},{"year":1948,"month":8,"value":17.26},{"year":1948,"month":9,"value":13.81},{"year":1948,"month":10,"value":5.24},{"year":1948,"month":11,"value":0.4},{"year":1948,"month":12,"value":-2.77},{"year":1949,"month":1,"value":-4.17},{"year":1949,"month":2,"value":-8.12},{"year":1949,"month":3,"value":-1.27},{"year":1949,"month":4,"value":7.05},{"year":1949,"month":5,"value":13.69},{"year":1949,"month":6,"value":15.9},{"year":1949,"month":7,"value":16.78},{"year":1949,"month":8,"value":16.7},{"year":1949,"month":9,"value":12.42},{"year":1949,"month":10,"value":6.45},{"year":1949,"month":11,"value":1.48},{"year":1949,"month":12,"value":-0.82},{"year":1950,"month":1,"value":-1.68},{"year":1950,"month":2,"value":-2.48},{"year":1950,"month":3,"value":-2.34},{"year":1950,"month":4,"value":5.76},{"year":1950,"month":5,"value":13.13},{"year":1950,"month":6,"value":14.84},{"year":1950,"month":7,"value":17.15},{"year":1950,"month":8,"value":14.86},{"year":1950,"month":9,"value":13.7},{"year":1950,"month":10,"value":7.24},{"year":1950,"month":11,"value":2.96},{"year":1950,"month":12,"value":0.44},{"year":1951,"month":1,"value":-12.57},{"year":1951,"month":2,"value":-2.66},{"year":1951,"month":3,"value":-0.72},{"year":1951,"month":4,"value":7.59},{"year":1951,"month":5,"value":11.5},{"year":1951,"month":6,"value":14.64},{"year":1951,"month":7,"value":15.87},{"year":1951,"month":8,"value":15.98},{"year":1951,"month":9,"value":12.59},{"year":1951,"month":10,"value":5.95},{"year":1951,"month":11,"value":1.06},{"year":1951,"month":12,"value":-1},{"year":1952,"month":1,"value":-7.02},{"year":1952,"month":2,"value":-5.4},{"year":1952,"month":3,"value":-4.16},{"year":1952,"month":4,"value":6.04},{"year":1952,"month":5,"value":8.33},{"year":1952,"month":6,"value":14.97},{"year":1952,"month":7,"value":16.22},{"year":1952,"month":8,"value":18.24},{"year":1952,"month":9,"value":12.7},{"year":1952,"month":10,"value":5.35},{"year":1952,"month":11,"value":0.86},{"year":1952,"month":12,"value":0.74},{"year":1953,"month":1,"value":-1.53},{"year":1953,"month":2,"value":-4.41},{"year":1953,"month":3,"value":-8.85},{"year":1953,"month":4,"value":6.19},{"year":1953,"month":5,"value":8.93},{"year":1953,"month":6,"value":13.72},{"year":1953,"month":7,"value":16.61},{"year":1953,"month":8,"value":16.12},{"year":1953,"month":9,"value":9.74},{"year":1953,"month":10,"value":5.1},{"year":1953,"month":11,"value":-0.54},{"year":1953,"month":12,"value":-2.58},{"year":1954,"month":1,"value":-5.46},{"year":1954,"month":2,"value":-7.92},{"year":1954,"month":3,"value":-1},{"year":1954,"month":4,"value":6.25},{"year":1954,"month":5,"value":10.69},{"year":1954,"month":6,"value":17},{"year":1954,"month":7,"value":17.79},{"year":1954,"month":8,"value":15.74},{"year":1954,"month":9,"value":11.65},{"year":1954,"month":10,"value":7.9},{"year":1954,"month":11,"value":0.82},{"year":1954,"month":12,"value":-3.36},{"year":1955,"month":1,"value":-8.82},{"year":1955,"month":2,"value":-12.52},{"year":1955,"month":3,"value":-0.22},{"year":1955,"month":4,"value":2.42},{"year":1955,"month":5,"value":12.88},{"year":1955,"month":6,"value":16.33},{"year":1955,"month":7,"value":16.82},{"year":1955,"month":8,"value":15.9},{"year":1955,"month":9,"value":12.31},{"year":1955,"month":10,"value":6.8},{"year":1955,"month":11,"value":0.36},{"year":1955,"month":12,"value":-0.19},{"year":1956,"month":1,"value":-4.48},{"year":1956,"month":2,"value":-5.77},{"year":1956,"month":3,"value":-4.22},{"year":1956,"month":4,"value":0.41},{"year":1956,"month":5,"value":8.04},{"year":1956,"month":6,"value":13.01},{"year":1956,"month":7,"value":17.78},{"year":1956,"month":8,"value":18.29},{"year":1956,"month":9,"value":14.1},{"year":1956,"month":10,"value":7.68},{"year":1956,"month":11,"value":0.89},{"year":1956,"month":12,"value":-5.58},{"year":1957,"month":1,"value":-5.9},{"year":1957,"month":2,"value":-13.54},{"year":1957,"month":3,"value":-3.96},{"year":1957,"month":4,"value":1.13},{"year":1957,"month":5,"value":9.88},{"year":1957,"month":6,"value":17.46},{"year":1957,"month":7,"value":15.45},{"year":1957,"month":8,"value":13.43},{"year":1957,"month":9,"value":9.62},{"year":1957,"month":10,"value":6.07},{"year":1957,"month":11,"value":-1.99},{"year":1957,"month":12,"value":-1.46},{"year":1958,"month":1,"value":-1.47},{"year":1958,"month":2,"value":-0.67},{"year":1958,"month":3,"value":-3.64},{"year":1958,"month":4,"value":4.79},{"year":1958,"month":5,"value":10.31},{"year":1958,"month":6,"value":14.13},{"year":1958,"month":7,"value":17.76},{"year":1958,"month":8,"value":15.48},{"year":1958,"month":9,"value":10.48},{"year":1958,"month":10,"value":7.65},{"year":1958,"month":11,"value":2.45},{"year":1958,"month":12,"value":-2.12},{"year":1959,"month":1,"value":-5.32},{"year":1959,"month":2,"value":-5.89},{"year":1959,"month":3,"value":-5.51},{"year":1959,"month":4,"value":2.4},{"year":1959,"month":5,"value":11.03},{"year":1959,"month":6,"value":13.98},{"year":1959,"month":7,"value":16.3},{"year":1959,"month":8,"value":15.07},{"year":1959,"month":9,"value":11.16},{"year":1959,"month":10,"value":8.06},{"year":1959,"month":11,"value":2.93},{"year":1959,"month":12,"value":-2.87},{"year":1960,"month":1,"value":-2.39},{"year":1960,"month":2,"value":-1.74},{"year":1960,"month":3,"value":1.14},{"year":1960,"month":4,"value":6.17},{"year":1960,"month":5,"value":10.01},{"year":1960,"month":6,"value":15.59},{"year":1960,"month":7,"value":19.22},{"year":1960,"month":8,"value":17.55},{"year":1960,"month":9,"value":9.62},{"year":1960,"month":10,"value":5.93},{"year":1960,"month":11,"value":0.98},{"year":1960,"month":12,"value":-6.04},{"year":1961,"month":1,"value":-7.5},{"year":1961,"month":2,"value":-7.18},{"year":1961,"month":3,"value":-3.92},{"year":1961,"month":4,"value":4.45},{"year":1961,"month":5,"value":11.34},{"year":1961,"month":6,"value":15.74},{"year":1961,"month":7,"value":17.7},{"year":1961,"month":8,"value":16},{"year":1961,"month":9,"value":10.75},{"year":1961,"month":10,"value":5.16},{"year":1961,"month":11,"value":1.78},{"year":1961,"month":12,"value":1.85},{"year":1962,"month":1,"value":-2.57},{"year":1962,"month":2,"value":0.3},{"year":1962,"month":3,"value":2},{"year":1962,"month":4,"value":5.64},{"year":1962,"month":5,"value":10.7},{"year":1962,"month":6,"value":16.96},{"year":1962,"month":7,"value":15.9},{"year":1962,"month":8,"value":14.69},{"year":1962,"month":9,"value":11.37},{"year":1962,"month":10,"value":8.64},{"year":1962,"month":11,"value":2.58},{"year":1962,"month":12,"value":-3.51},{"year":1963,"month":1,"value":-1.53},{"year":1963,"month":2,"value":-4.42},{"year":1963,"month":3,"value":-6.15},{"year":1963,"month":4,"value":6.41},{"year":1963,"month":5,"value":9.23},{"year":1963,"month":6,"value":12.55},{"year":1963,"month":7,"value":14.87},{"year":1963,"month":8,"value":14.22},{"year":1963,"month":9,"value":10.68},{"year":1963,"month":10,"value":7.65},{"year":1963,"month":11,"value":2.14},{"year":1963,"month":12,"value":-5.16},{"year":1964,"month":1,"value":-11.34},{"year":1964,"month":2,"value":-9.91},{"year":1964,"month":3,"value":-7},{"year":1964,"month":4,"value":3.98},{"year":1964,"month":5,"value":14.67},{"year":1964,"month":6,"value":14.25},{"year":1964,"month":7,"value":18.25},{"year":1964,"month":8,"value":17.56},{"year":1964,"month":9,"value":13.38},{"year":1964,"month":10,"value":7.11},{"year":1964,"month":11,"value":1.31},{"year":1964,"month":12,"value":-5.63},{"year":1965,"month":1,"value":-3.25},{"year":1965,"month":2,"value":-8.58},{"year":1965,"month":3,"value":-5.19},{"year":1965,"month":4,"value":4.64},{"year":1965,"month":5,"value":10.83},{"year":1965,"month":6,"value":17.26},{"year":1965,"month":7,"value":17.3},{"year":1965,"month":8,"value":14.83},{"year":1965,"month":9,"value":11.51},{"year":1965,"month":10,"value":7.27},{"year":1965,"month":11,"value":1.28},{"year":1965,"month":12,"value":-1.7},{"year":1966,"month":1,"value":-3.93},{"year":1966,"month":2,"value":-7.7},{"year":1966,"month":3,"value":-2.69},{"year":1966,"month":4,"value":4.31},{"year":1966,"month":5,"value":7.92},{"year":1966,"month":6,"value":14.97},{"year":1966,"month":7,"value":14.68},{"year":1966,"month":8,"value":14.73},{"year":1966,"month":9,"value":13.45},{"year":1966,"month":10,"value":6.83},{"year":1966,"month":11,"value":-3.7},{"year":1966,"month":12,"value":-2.21},{"year":1967,"month":1,"value":-9.49},{"year":1967,"month":2,"value":-8.85},{"year":1967,"month":3,"value":-0.24},{"year":1967,"month":4,"value":3.44},{"year":1967,"month":5,"value":12.21},{"year":1967,"month":6,"value":17.04},{"year":1967,"month":7,"value":17.6},{"year":1967,"month":8,"value":15.08},{"year":1967,"month":9,"value":10.46},{"year":1967,"month":10,"value":7.26},{"year":1967,"month":11,"value":0.71},{"year":1967,"month":12,"value":-4.58},{"year":1968,"month":1,"value":-10.77},{"year":1968,"month":2,"value":-3.65},{"year":1968,"month":3,"value":2.01},{"year":1968,"month":4,"value":4.94},{"year":1968,"month":5,"value":12.65},{"year":1968,"month":6,"value":14.59},{"year":1968,"month":7,"value":17.08},{"year":1968,"month":8,"value":16.04},{"year":1968,"month":9,"value":13.46},{"year":1968,"month":10,"value":9.91},{"year":1968,"month":11,"value":3.34},{"year":1968,"month":12,"value":-6.56},{"year":1969,"month":1,"value":-10.94},{"year":1969,"month":2,"value":-5.39},{"year":1969,"month":3,"value":-0.5},{"year":1969,"month":4,"value":5.99},{"year":1969,"month":5,"value":9.56},{"year":1969,"month":6,"value":16.62},{"year":1969,"month":7,"value":15.24},{"year":1969,"month":8,"value":17.14},{"year":1969,"month":9,"value":11.85},{"year":1969,"month":10,"value":5.03},{"year":1969,"month":11,"value":-0.05},{"year":1969,"month":12,"value":-2.59},{"year":1970,"month":1,"value":-11.04},{"year":1970,"month":2,"value":-8.05},{"year":1970,"month":3,"value":-5.9},{"year":1970,"month":4,"value":4.4},{"year":1970,"month":5,"value":10.35},{"year":1970,"month":6,"value":15.09},{"year":1970,"month":7,"value":17.25},{"year":1970,"month":8,"value":15.91},{"year":1970,"month":9,"value":10.98},{"year":1970,"month":10,"value":6.39},{"year":1970,"month":11,"value":2.23},{"year":1970,"month":12,"value":-8.37},{"year":1971,"month":1,"value":-10.15},{"year":1971,"month":2,"value":-9.7},{"year":1971,"month":3,"value":-1.44},{"year":1971,"month":4,"value":4.32},{"year":1971,"month":5,"value":11.47},{"year":1971,"month":6,"value":16.02},{"year":1971,"month":7,"value":16.56},{"year":1971,"month":8,"value":15.8},{"year":1971,"month":9,"value":10.91},{"year":1971,"month":10,"value":5.37},{"year":1971,"month":11,"value":1.22},{"year":1971,"month":12,"value":-3.04},{"year":1972,"month":1,"value":-1.9},{"year":1972,"month":2,"value":-3.32},{"year":1972,"month":3,"value":-3.43},{"year":1972,"month":4,"value":4.63},{"year":1972,"month":5,"value":12.31},{"year":1972,"month":6,"value":14.81},{"year":1972,"month":7,"value":17.07},{"year":1972,"month":8,"value":16.86},{"year":1972,"month":9,"value":10.44},{"year":1972,"month":10,"value":6.53},{"year":1972,"month":11,"value":-0.32},{"year":1972,"month":12,"value":-0.05},{"year":1973,"month":1,"value":-10.55},{"year":1973,"month":2,"value":-2.91},{"year":1973,"month":3,"value":-0.67},{"year":1973,"month":4,"value":4.1},{"year":1973,"month":5,"value":11.02},{"year":1973,"month":6,"value":17.08},{"year":1973,"month":7,"value":19.76},{"year":1973,"month":8,"value":17.44},{"year":1973,"month":9,"value":11.11},{"year":1973,"month":10,"value":5.19},{"year":1973,"month":11,"value":2.39},{"year":1973,"month":12,"value":0.95},{"year":1974,"month":1,"value":-3.93},{"year":1974,"month":2,"value":-1.51},{"year":1974,"month":3,"value":1.26},{"year":1974,"month":4,"value":4.81},{"year":1974,"month":5,"value":11.01},{"year":1974,"month":6,"value":16.43},{"year":1974,"month":7,"value":18.56},{"year":1974,"month":8,"value":15.68},{"year":1974,"month":9,"value":8.93},{"year":1974,"month":10,"value":4.34},{"year":1974,"month":11,"value":-0.03},{"year":1974,"month":12,"value":-4},{"year":1975,"month":1,"value":-3.21},{"year":1975,"month":2,"value":-0.25},{"year":1975,"month":3,"value":0.59},{"year":1975,"month":4,"value":3.91},{"year":1975,"month":5,"value":8.47},{"year":1975,"month":6,"value":14.45},{"year":1975,"month":7,"value":15.44},{"year":1975,"month":8,"value":15.5},{"year":1975,"month":9,"value":12.79},{"year":1975,"month":10,"value":6.77},{"year":1975,"month":11,"value":2.62},{"year":1975,"month":12,"value":0.67},{"year":1976,"month":1,"value":0.03},{"year":1976,"month":2,"value":-1.67},{"year":1976,"month":3,"value":1.66},{"year":1976,"month":4,"value":5.3},{"year":1976,"month":5,"value":13.17},{"year":1976,"month":6,"value":14.61},{"year":1976,"month":7,"value":18.01},{"year":1976,"month":8,"value":17.22},{"year":1976,"month":9,"value":14.38},{"year":1976,"month":10,"value":6.63},{"year":1976,"month":11,"value":-0.09},{"year":1976,"month":12,"value":0.15},{"year":1977,"month":1,"value":-7.28},{"year":1977,"month":2,"value":-7.28},{"year":1977,"month":3,"value":-3.63},{"year":1977,"month":4,"value":3.85},{"year":1977,"month":5,"value":10.52},{"year":1977,"month":6,"value":12.44},{"year":1977,"month":7,"value":16.59},{"year":1977,"month":8,"value":14.83},{"year":1977,"month":9,"value":10.4},{"year":1977,"month":10,"value":1.85},{"year":1977,"month":11,"value":2.27},{"year":1977,"month":12,"value":-3.33},{"year":1978,"month":1,"value":-5.89},{"year":1978,"month":2,"value":-5.41},{"year":1978,"month":3,"value":-0.45},{"year":1978,"month":4,"value":3.86},{"year":1978,"month":5,"value":11.35},{"year":1978,"month":6,"value":15.38},{"year":1978,"month":7,"value":15.16},{"year":1978,"month":8,"value":14.81},{"year":1978,"month":9,"value":9.57},{"year":1978,"month":10,"value":6.49},{"year":1978,"month":11,"value":3.18},{"year":1978,"month":12,"value":-3.59},{"year":1979,"month":1,"value":-4.72},{"year":1979,"month":2,"value":-8.06},{"year":1979,"month":3,"value":0.68},{"year":1979,"month":4,"value":3.92},{"year":1979,"month":5,"value":10.09},{"year":1979,"month":6,"value":14},{"year":1979,"month":7,"value":15.36},{"year":1979,"month":8,"value":15.16},{"year":1979,"month":9,"value":9.44},{"year":1979,"month":10,"value":5.6},{"year":1979,"month":11,"value":5.05},{"year":1979,"month":12,"value":-11.8},{"year":1980,"month":1,"value":-8.32},{"year":1980,"month":2,"value":-8.14},{"year":1980,"month":3,"value":-0.82},{"year":1980,"month":4,"value":3.66},{"year":1980,"month":5,"value":12.87},{"year":1980,"month":6,"value":17.27},{"year":1980,"month":7,"value":14.11},{"year":1980,"month":8,"value":16.33},{"year":1980,"month":9,"value":11.55},{"year":1980,"month":10,"value":4.88},{"year":1980,"month":11,"value":1.43},{"year":1980,"month":12,"value":-1.95},{"year":1981,"month":1,"value":-7.96},{"year":1981,"month":2,"value":-7.41},{"year":1981,"month":3,"value":-4.98},{"year":1981,"month":4,"value":5.35},{"year":1981,"month":5,"value":7.48},{"year":1981,"month":6,"value":16.53},{"year":1981,"month":7,"value":16.44},{"year":1981,"month":8,"value":14.9},{"year":1981,"month":9,"value":11.55},{"year":1981,"month":10,"value":6.66},{"year":1981,"month":11,"value":-0.63},{"year":1981,"month":12,"value":-1.33},{"year":1982,"month":1,"value":-4.32},{"year":1982,"month":2,"value":-3.79},{"year":1982,"month":3,"value":-2.11},{"year":1982,"month":4,"value":2.85},{"year":1982,"month":5,"value":13.12},{"year":1982,"month":6,"value":15.24},{"year":1982,"month":7,"value":17.16},{"year":1982,"month":8,"value":15.13},{"year":1982,"month":9,"value":11.78},{"year":1982,"month":10,"value":7.71},{"year":1982,"month":11,"value":1.21},{"year":1982,"month":12,"value":-4.63},{"year":1983,"month":1,"value":-6.65},{"year":1983,"month":2,"value":-4.98},{"year":1983,"month":3,"value":0.38},{"year":1983,"month":4,"value":4.16},{"year":1983,"month":5,"value":11.04},{"year":1983,"month":6,"value":12.6},{"year":1983,"month":7,"value":17.23},{"year":1983,"month":8,"value":16.52},{"year":1983,"month":9,"value":11.71},{"year":1983,"month":10,"value":6.8},{"year":1983,"month":11,"value":4.14},{"year":1983,"month":12,"value":0.31},{"year":1984,"month":1,"value":0.58},{"year":1984,"month":2,"value":-5.69},{"year":1984,"month":3,"value":-0.99},{"year":1984,"month":4,"value":7.13},{"year":1984,"month":5,"value":13.75},{"year":1984,"month":6,"value":14.26},{"year":1984,"month":7,"value":17.32},{"year":1984,"month":8,"value":16.89},{"year":1984,"month":9,"value":12.98},{"year":1984,"month":10,"value":7.59},{"year":1984,"month":11,"value":1.04},{"year":1984,"month":12,"value":-1.53},{"year":1985,"month":1,"value":-2.43},{"year":1985,"month":2,"value":-5.28},{"year":1985,"month":3,"value":-1.95},{"year":1985,"month":4,"value":7.29},{"year":1985,"month":5,"value":13.58},{"year":1985,"month":6,"value":14.02},{"year":1985,"month":7,"value":15.33},{"year":1985,"month":8,"value":16.2},{"year":1985,"month":9,"value":11.19},{"year":1985,"month":10,"value":8.98},{"year":1985,"month":11,"value":0.46},{"year":1985,"month":12,"value":-2.88},{"year":1986,"month":1,"value":-11.37},{"year":1986,"month":2,"value":-13.71},{"year":1986,"month":3,"value":-1.07},{"year":1986,"month":4,"value":3.37},{"year":1986,"month":5,"value":12.26},{"year":1986,"month":6,"value":14.26},{"year":1986,"month":7,"value":15.81},{"year":1986,"month":8,"value":17.35},{"year":1986,"month":9,"value":10.22},{"year":1986,"month":10,"value":8.51},{"year":1986,"month":11,"value":-0.48},{"year":1986,"month":12,"value":-3.66},{"year":1987,"month":1,"value":-4.16},{"year":1987,"month":2,"value":-10.81},{"year":1987,"month":3,"value":0.34},{"year":1987,"month":4,"value":5.1},{"year":1987,"month":5,"value":12.46},{"year":1987,"month":6,"value":16.17},{"year":1987,"month":7,"value":17},{"year":1987,"month":8,"value":15.36},{"year":1987,"month":9,"value":8.77},{"year":1987,"month":10,"value":6.56},{"year":1987,"month":11,"value":3.83},{"year":1987,"month":12,"value":-4.06},{"year":1988,"month":1,"value":-15.05},{"year":1988,"month":2,"value":-4.11},{"year":1988,"month":3,"value":-5.27},{"year":1988,"month":4,"value":3.72},{"year":1988,"month":5,"value":10.03},{"year":1988,"month":6,"value":13.97},{"year":1988,"month":7,"value":15.5},{"year":1988,"month":8,"value":14.14},{"year":1988,"month":9,"value":10.39},{"year":1988,"month":10,"value":6.42},{"year":1988,"month":11,"value":1.3},{"year":1988,"month":12,"value":-2.44},{"year":1989,"month":1,"value":-2.67},{"year":1989,"month":2,"value":-2.81},{"year":1989,"month":3,"value":-1.18},{"year":1989,"month":4,"value":3.87},{"year":1989,"month":5,"value":13.35},{"year":1989,"month":6,"value":16.88},{"year":1989,"month":7,"value":19.09},{"year":1989,"month":8,"value":15.34},{"year":1989,"month":9,"value":12.62},{"year":1989,"month":10,"value":5.94},{"year":1989,"month":11,"value":-1.73},{"year":1989,"month":12,"value":-3.55},{"year":1990,"month":1,"value":1.5},{"year":1990,"month":2,"value":2},{"year":1990,"month":3,"value":3.15},{"year":1990,"month":4,"value":7.16},{"year":1990,"month":5,"value":12.05},{"year":1990,"month":6,"value":16},{"year":1990,"month":7,"value":17.39},{"year":1990,"month":8,"value":15.43},{"year":1990,"month":9,"value":12.47},{"year":1990,"month":10,"value":6.92},{"year":1990,"month":11,"value":0.61},{"year":1990,"month":12,"value":-2.59},{"year":1991,"month":1,"value":-0.17},{"year":1991,"month":2,"value":3.23},{"year":1991,"month":3,"value":3.79},{"year":1991,"month":4,"value":7.6},{"year":1991,"month":5,"value":10.61},{"year":1991,"month":6,"value":14.61},{"year":1991,"month":7,"value":15.45},{"year":1991,"month":8,"value":15.98},{"year":1991,"month":9,"value":9.8},{"year":1991,"month":10,"value":6.75},{"year":1991,"month":11,"value":2.65},{"year":1991,"month":12,"value":-1.44},{"year":1992,"month":1,"value":-1.16},{"year":1992,"month":2,"value":-4.28},{"year":1992,"month":3,"value":0.99},{"year":1992,"month":4,"value":5.78},{"year":1992,"month":5,"value":9.05},{"year":1992,"month":6,"value":13.72},{"year":1992,"month":7,"value":17.39},{"year":1992,"month":8,"value":17.1},{"year":1992,"month":9,"value":12.06},{"year":1992,"month":10,"value":6.92},{"year":1992,"month":11,"value":3.4},{"year":1992,"month":12,"value":-0.58},{"year":1993,"month":1,"value":-0.46},{"year":1993,"month":2,"value":-0.89},{"year":1993,"month":3,"value":1.97},{"year":1993,"month":4,"value":4.04},{"year":1993,"month":5,"value":11.96},{"year":1993,"month":6,"value":16.14},{"year":1993,"month":7,"value":17.66},{"year":1993,"month":8,"value":17.39},{"year":1993,"month":9,"value":12.48},{"year":1993,"month":10,"value":2.75},{"year":1993,"month":11,"value":0.25},{"year":1993,"month":12,"value":-0.32},{"year":1994,"month":1,"value":-1.34},{"year":1994,"month":2,"value":-1.46},{"year":1994,"month":3,"value":-0.6},{"year":1994,"month":4,"value":6.14},{"year":1994,"month":5,"value":14.77},{"year":1994,"month":6,"value":13.03},{"year":1994,"month":7,"value":16.06},{"year":1994,"month":8,"value":14.43},{"year":1994,"month":9,"value":8.08},{"year":1994,"month":10,"value":5.5},{"year":1994,"month":11,"value":-4.99},{"year":1994,"month":12,"value":-1.2},{"year":1995,"month":1,"value":-1.44},{"year":1995,"month":2,"value":-10.04},{"year":1995,"month":3,"value":-0.87},{"year":1995,"month":4,"value":7.57},{"year":1995,"month":5,"value":9.7},{"year":1995,"month":6,"value":13.18},{"year":1995,"month":7,"value":19.46},{"year":1995,"month":8,"value":16.53},{"year":1995,"month":9,"value":12.88},{"year":1995,"month":10,"value":5.27},{"year":1995,"month":11,"value":1.02},{"year":1995,"month":12,"value":-1.5},{"year":1996,"month":1,"value":-3.87},{"year":1996,"month":2,"value":1.1},{"year":1996,"month":3,"value":1.43},{"year":1996,"month":4,"value":5.76},{"year":1996,"month":5,"value":11.15},{"year":1996,"month":6,"value":17.37},{"year":1996,"month":7,"value":16.91},{"year":1996,"month":8,"value":16.59},{"year":1996,"month":9,"value":11.74},{"year":1996,"month":10,"value":8.52},{"year":1996,"month":11,"value":-0.81},{"year":1996,"month":12,"value":-6.8},{"year":1997,"month":1,"value":-7.58},{"year":1997,"month":2,"value":-9.53},{"year":1997,"month":3,"value":-3.16},{"year":1997,"month":4,"value":6.03},{"year":1997,"month":5,"value":11.91},{"year":1997,"month":6,"value":14.31},{"year":1997,"month":7,"value":15.2},{"year":1997,"month":8,"value":18.04},{"year":1997,"month":9,"value":9.29},{"year":1997,"month":10,"value":7.63},{"year":1997,"month":11,"value":4.04},{"year":1997,"month":12,"value":-5.9},{"year":1998,"month":1,"value":-3.25},{"year":1998,"month":2,"value":-0.93},{"year":1998,"month":3,"value":-0.13},{"year":1998,"month":4,"value":3.25},{"year":1998,"month":5,"value":9.57},{"year":1998,"month":6,"value":15.83},{"year":1998,"month":7,"value":18.28},{"year":1998,"month":8,"value":18.84},{"year":1998,"month":9,"value":11.3},{"year":1998,"month":10,"value":4.82},{"year":1998,"month":11,"value":1.57},{"year":1998,"month":12,"value":-4.05},{"year":1999,"month":1,"value":-0.28},{"year":1999,"month":2,"value":-0.87},{"year":1999,"month":3,"value":-1.25},{"year":1999,"month":4,"value":6.98},{"year":1999,"month":5,"value":12.15},{"year":1999,"month":6,"value":15.92},{"year":1999,"month":7,"value":16.02},{"year":1999,"month":8,"value":14.31},{"year":1999,"month":9,"value":11.63},{"year":1999,"month":10,"value":6.26},{"year":1999,"month":11,"value":-5.23},{"year":1999,"month":12,"value":-3.48},{"year":2000,"month":1,"value":-3.03},{"year":2000,"month":2,"value":-5.14},{"year":2000,"month":3,"value":1.09},{"year":2000,"month":4,"value":8.53},{"year":2000,"month":5,"value":9.09},{"year":2000,"month":6,"value":18.6},{"year":2000,"month":7,"value":19.17},{"year":2000,"month":8,"value":16},{"year":2000,"month":9,"value":13.57},{"year":2000,"month":10,"value":6.93},{"year":2000,"month":11,"value":1.4},{"year":2000,"month":12,"value":-0.7},{"year":2001,"month":1,"value":-2.49},{"year":2001,"month":2,"value":-0.01},{"year":2001,"month":3,"value":0.77},{"year":2001,"month":4,"value":9.8},{"year":2001,"month":5,"value":11.56},{"year":2001,"month":6,"value":14.41},{"year":2001,"month":7,"value":16.06},{"year":2001,"month":8,"value":15.54},{"year":2001,"month":9,"value":9.9},{"year":2001,"month":10,"value":9.25},{"year":2001,"month":11,"value":4.55},{"year":2001,"month":12,"value":0.88},{"year":2002,"month":1,"value":-1.34},{"year":2002,"month":2,"value":-4.21},{"year":2002,"month":3,"value":-0.82},{"year":2002,"month":4,"value":7.39},{"year":2002,"month":5,"value":11.08},{"year":2002,"month":6,"value":14.24},{"year":2002,"month":7,"value":20.69},{"year":2002,"month":8,"value":16.9},{"year":2002,"month":9,"value":11.97},{"year":2002,"month":10,"value":8.41},{"year":2002,"month":11,"value":0.92},{"year":2002,"month":12,"value":-6.89},{"year":2003,"month":1,"value":-1.77},{"year":2003,"month":2,"value":0.86},{"year":2003,"month":3,"value":2.12},{"year":2003,"month":4,"value":6.68},{"year":2003,"month":5,"value":14.03},{"year":2003,"month":6,"value":16.07},{"year":2003,"month":7,"value":19.57},{"year":2003,"month":8,"value":19.2},{"year":2003,"month":9,"value":11.94},{"year":2003,"month":10,"value":2.65},{"year":2003,"month":11,"value":0.49},{"year":2003,"month":12,"value":-8.3},{"year":2004,"month":1,"value":-5.73},{"year":2004,"month":2,"value":-5.71},{"year":2004,"month":3,"value":0.05},{"year":2004,"month":4,"value":4.07},{"year":2004,"month":5,"value":12.43},{"year":2004,"month":6,"value":14.16},{"year":2004,"month":7,"value":19.88},{"year":2004,"month":8,"value":16.01},{"year":2004,"month":9,"value":12.14},{"year":2004,"month":10,"value":4.56},{"year":2004,"month":11,"value":3.02},{"year":2004,"month":12,"value":0.69},{"year":2005,"month":1,"value":-6.93},{"year":2005,"month":2,"value":-3.14},{"year":2005,"month":3,"value":0.67},{"year":2005,"month":4,"value":6.37},{"year":2005,"month":5,"value":10.34},{"year":2005,"month":6,"value":13.62},{"year":2005,"month":7,"value":16.65},{"year":2005,"month":8,"value":17.59},{"year":2005,"month":9,"value":12.55},{"year":2005,"month":10,"value":6.97},{"year":2005,"month":11,"value":0.19},{"year":2005,"month":12,"value":0.81},{"year":2006,"month":1,"value":-0.78},{"year":2006,"month":2,"value":-6.29},{"year":2006,"month":3,"value":-4.96},{"year":2006,"month":4,"value":5.95},{"year":2006,"month":5,"value":11.12},{"year":2006,"month":6,"value":14.49},{"year":2006,"month":7,"value":18.48},{"year":2006,"month":8,"value":16.32},{"year":2006,"month":9,"value":13.51},{"year":2006,"month":10,"value":7.27},{"year":2006,"month":11,"value":2.88},{"year":2006,"month":12,"value":-2.7},{"year":2007,"month":1,"value":-6.61},{"year":2007,"month":2,"value":-7.44},{"year":2007,"month":3,"value":-3.69},{"year":2007,"month":4,"value":5.76},{"year":2007,"month":5,"value":11.34},{"year":2007,"month":6,"value":16.16},{"year":2007,"month":7,"value":19.63},{"year":2007,"month":8,"value":17.5},{"year":2007,"month":9,"value":14.07},{"year":2007,"month":10,"value":9.21},{"year":2007,"month":11,"value":3.73},{"year":2007,"month":12,"value":4.05},{"year":2008,"month":1,"value":0.09},{"year":2008,"month":2,"value":-8.77},{"year":2008,"month":3,"value":4.61},{"year":2008,"month":4,"value":5.44},{"year":2008,"month":5,"value":12.61},{"year":2008,"month":6,"value":16.65},{"year":2008,"month":7,"value":16.65},{"year":2008,"month":8,"value":18.2},{"year":2008,"month":9,"value":11.91},{"year":2008,"month":10,"value":7.18},{"year":2008,"month":11,"value":1.02},{"year":2008,"month":12,"value":1.09},{"year":2009,"month":1,"value":-0.78},{"year":2009,"month":2,"value":1.54},{"year":2009,"month":3,"value":1.36},{"year":2009,"month":4,"value":7.57},{"year":2009,"month":5,"value":10.91},{"year":2009,"month":6,"value":14.99},{"year":2009,"month":7,"value":17.23},{"year":2009,"month":8,"value":16.97},{"year":2009,"month":9,"value":10.93},{"year":2009,"month":10,"value":8.56},{"year":2009,"month":11,"value":2.74},{"year":2009,"month":12,"value":-0.11},{"year":2010,"month":1,"value":-2.7},{"year":2010,"month":2,"value":-4.02},{"year":2010,"month":3,"value":-0.26},{"year":2010,"month":4,"value":7.19},{"year":2010,"month":5,"value":11.61},{"year":2010,"month":6,"value":14.25},{"year":2010,"month":7,"value":17.46},{"year":2010,"month":8,"value":15.86},{"year":2010,"month":9,"value":13.35},{"year":2010,"month":10,"value":4.63},{"year":2010,"month":11,"value":3.34},{"year":2010,"month":12,"value":-3.42},{"year":2011,"month":1,"value":-12.23},{"year":2011,"month":2,"value":-5.69},{"year":2011,"month":3,"value":-0.88},{"year":2011,"month":4,"value":6.48},{"year":2011,"month":5,"value":12.73},{"year":2011,"month":6,"value":15.32},{"year":2011,"month":7,"value":21.71},{"year":2011,"month":8,"value":18.84},{"year":2011,"month":9,"value":11.29},{"year":2011,"month":10,"value":4.61},{"year":2011,"month":11,"value":2.01},{"year":2011,"month":12,"value":-7.1},{"year":2012,"month":1,"value":-3.42},{"year":2012,"month":2,"value":-9.35},{"year":2012,"month":3,"value":-0.62},{"year":2012,"month":4,"value":7.25},{"year":2012,"month":5,"value":11.64},{"year":2012,"month":6,"value":17.43},{"year":2012,"month":7,"value":19.96},{"year":2012,"month":8,"value":16.76},{"year":2012,"month":9,"value":13.11},{"year":2012,"month":10,"value":7.45},{"year":2012,"month":11,"value":3.93},{"year":2012,"month":12,"value":1.85},{"year":2013,"month":1,"value":-3.93},{"year":2013,"month":2,"value":-9.57},{"year":2013,"month":3,"value":0.83},{"year":2013,"month":4,"value":6.18},{"year":2013,"month":5,"value":12.11},{"year":2013,"month":6,"value":14.13},{"year":2013,"month":7,"value":18.35},{"year":2013,"month":8,"value":15.76},{"year":2013,"month":9,"value":12.8},{"year":2013,"month":10,"value":6.62},{"year":2013,"month":11,"value":3.75},{"year":2013,"month":12,"value":-5.1},{"year":2014,"month":1,"value":-6.91},{"year":2014,"month":2,"value":-2.45},{"year":2014,"month":3,"value":-5.93},{"year":2014,"month":4,"value":4.26},{"year":2014,"month":5,"value":14.92},{"year":2014,"month":6,"value":17.86},{"year":2014,"month":7,"value":17.86},{"year":2014,"month":8,"value":17.01},{"year":2014,"month":9,"value":11.6},{"year":2014,"month":10,"value":7.85},{"year":2014,"month":11,"value":4.46},{"year":2014,"month":12,"value":1.81},{"year":2015,"month":1,"value":-6.67},{"year":2015,"month":2,"value":0.25},{"year":2015,"month":3,"value":3.47},{"year":2015,"month":4,"value":7.42},{"year":2015,"month":5,"value":12.33},{"year":2015,"month":6,"value":13.86},{"year":2015,"month":7,"value":19.78},{"year":2015,"month":8,"value":17.08},{"year":2015,"month":9,"value":12.48},{"year":2015,"month":10,"value":6.24},{"year":2015,"month":11,"value":1.89},{"year":2015,"month":12,"value":-1.18},{"year":2016,"month":1,"value":-0.99},{"year":2016,"month":2,"value":-0.51},{"year":2016,"month":3,"value":3.47},{"year":2016,"month":4,"value":6.08},{"year":2016,"month":5,"value":10.53},{"year":2016,"month":6,"value":14.51},{"year":2016,"month":7,"value":16.37},{"year":2016,"month":8,"value":17.89},{"year":2016,"month":9,"value":13.1},{"year":2016,"month":10,"value":5.13},{"year":2016,"month":11,"value":4.24},{"year":2016,"month":12,"value":2.6},{"year":2017,"month":1,"value":-7.91},{"year":2017,"month":2,"value":1},{"year":2017,"month":3,"value":0.96},{"year":2017,"month":4,"value":6.3},{"year":2017,"month":5,"value":14.08},{"year":2017,"month":6,"value":16.47},{"year":2017,"month":7,"value":18.1},{"year":2017,"month":8,"value":16.51},{"year":2017,"month":9,"value":13},{"year":2017,"month":10,"value":4.51},{"year":2017,"month":11,"value":0.38},{"year":2017,"month":12,"value":0.55},{"year":2018,"month":1,"value":-3.28},{"year":2018,"month":2,"value":-2.62},{"year":2018,"month":3,"value":2.13},{"year":2018,"month":4,"value":4.13},{"year":2018,"month":5,"value":10.82},{"year":2018,"month":6,"value":14.17},{"year":2018,"month":7,"value":16},{"year":2018,"month":8,"value":16.67},{"year":2018,"month":9,"value":12.61},{"year":2018,"month":10,"value":6.2},{"year":2018,"month":11,"value":3.19},{"year":2018,"month":12,"value":0.9},{"year":2019,"month":1,"value":-1.81},{"year":2019,"month":2,"value":-7.23},{"year":2019,"month":3,"value":-2.43},{"year":2019,"month":4,"value":8.21},{"year":2019,"month":5,"value":15.52},{"year":2019,"month":6,"value":15.92},{"year":2019,"month":7,"value":19.95},{"year":2019,"month":8,"value":18.52},{"year":2019,"month":9,"value":14.34},{"year":2019,"month":10,"value":7.8},{"year":2019,"month":11,"value":2.56},{"year":2019,"month":12,"value":-1.43},{"year":2020,"month":1,"value":-4.47},{"year":2020,"month":2,"value":0.57},{"year":2020,"month":3,"value":2.25},{"year":2020,"month":4,"value":7.87},{"year":2020,"month":5,"value":11.94},{"year":2020,"month":6,"value":18.92},{"year":2020,"month":7,"value":16.04},{"year":2020,"month":8,"value":16.74},{"year":2020,"month":9,"value":12.04},{"year":2020,"month":10,"value":8.29},{"year":2020,"month":11,"value":3.89},{"year":2020,"month":12,"value":2.41},{"year":2021,"month":1,"value":2.75},{"year":2021,"month":2,"value":2},{"year":2021,"month":3,"value":2.76},{"year":2021,"month":4,"value":5.59},{"year":2021,"month":5,"value":9.65},{"year":2021,"month":6,"value":18.41},{"year":2021,"month":7,"value":16.51},{"year":2021,"month":8,"value":17.03},{"year":2021,"month":9,"value":14.2},{"year":2021,"month":10,"value":9.6},{"year":2021,"month":11,"value":4.99},{"year":2021,"month":12,"value":0.1},{"year":2022,"month":1,"value":-3.48},{"year":2022,"month":2,"value":-5.85},{"year":2022,"month":3,"value":1.2},{"year":2022,"month":4,"value":5.49},{"year":2022,"month":5,"value":10.74},{"year":2022,"month":6,"value":19.11},{"year":2022,"month":7,"value":21.47},{"year":2022,"month":8,"value":15.83},{"year":2022,"month":9,"value":10.67},{"year":2022,"month":10,"value":7.97},{"year":2022,"month":11,"value":3.32},{"year":2022,"month":12,"value":-4.31},{"year":2023,"month":1,"value":-1.2},{"year":2023,"month":2,"value":0.18},{"year":2023,"month":3,"value":0.8},{"year":2023,"month":4,"value":5.15},{"year":2023,"month":5,"value":10.14},{"year":2023,"month":6,"value":17.15},{"year":2023,"month":7,"value":17.62},{"year":2023,"month":8,"value":19.8},{"year":2023,"month":9,"value":9.88},{"year":2023,"month":10,"value":8.9},{"year":2023,"month":11,"value":2.26},{"year":2023,"month":12,"value":-3.33},{"year":2024,"month":1,"value":-0.87},{"year":2024,"month":2,"value":-1.23},{"year":2024,"month":3,"value":1.53},{"year":2024,"month":4,"value":7.68},{"year":2024,"month":5,"value":11.56},{"year":2024,"month":6,"value":16.8},{"year":2024,"month":7,"value":16.84},{"year":2024,"month":8,"value":18.74},{"year":2024,"month":9,"value":15.74},{"year":2024,"month":10,"value":6.75},{"year":2024,"month":11,"value":1.37},{"year":2024,"month":12,"value":-1.47},{"year":2025,"month":1,"value":-5.65},{"year":2025,"month":2,"value":0.41},{"year":2025,"month":3,"value":3.44},{"year":2025,"month":4,"value":7.59},{"year":2025,"month":5,"value":14.58},{"year":2025,"month":6,"value":17.2},{"year":2025,"month":7,"value":19.16},{"year":2025,"month":8,"value":18.02},{"year":2025,"month":9,"value":16.02},{"year":2025,"month":10,"value":8.21},{"year":2025,"month":11,"value":3.96},{"year":2025,"month":12,"value":1.4},{"year":2026,"month":1,"value":1.6},{"year":2026,"month":2,"value":-3.15},{"year":2026,"month":3,"value":3.92}],"precipYearly":[{"year":1940,"value":691.7},{"year":1941,"value":583.2},{"year":1942,"value":526.3},{"year":1943,"value":663},{"year":1944,"value":600},{"year":1945,"value":794.5},{"year":1946,"value":635.4},{"year":1947,"value":557.2},{"year":1948,"value":736.4},{"year":1949,"value":733.9,"rollingAvg":652.2},{"year":1950,"value":767.5,"rollingAvg":659.7},{"year":1951,"value":559.2,"rollingAvg":657.3},{"year":1952,"value":785.4,"rollingAvg":683.3},{"year":1953,"value":581.5,"rollingAvg":675.1},{"year":1954,"value":733.6,"rollingAvg":688.5},{"year":1955,"value":654.3,"rollingAvg":674.4},{"year":1956,"value":761.3,"rollingAvg":687},{"year":1957,"value":791.8,"rollingAvg":710.5},{"year":1958,"value":667.8,"rollingAvg":703.6},{"year":1959,"value":609.3,"rollingAvg":691.2},{"year":1960,"value":774.9,"rollingAvg":691.9},{"year":1961,"value":713.9,"rollingAvg":707.4},{"year":1962,"value":918,"rollingAvg":720.6},{"year":1963,"value":687.5,"rollingAvg":731.2},{"year":1964,"value":613,"rollingAvg":719.2},{"year":1965,"value":706.4,"rollingAvg":724.4},{"year":1966,"value":770.5,"rollingAvg":725.3},{"year":1967,"value":771.8,"rollingAvg":723.3},{"year":1968,"value":709,"rollingAvg":727.4},{"year":1969,"value":626.3,"rollingAvg":729.1},{"year":1970,"value":761.4,"rollingAvg":727.8},{"year":1971,"value":734.3,"rollingAvg":729.8},{"year":1972,"value":814.9,"rollingAvg":719.5},{"year":1973,"value":754.3,"rollingAvg":726.2},{"year":1974,"value":831.3,"rollingAvg":748},{"year":1975,"value":639.1,"rollingAvg":741.3},{"year":1976,"value":664.2,"rollingAvg":730.7},{"year":1977,"value":778.4,"rollingAvg":731.3},{"year":1978,"value":924.3,"rollingAvg":752.9},{"year":1979,"value":714.3,"rollingAvg":761.7},{"year":1980,"value":837.4,"rollingAvg":769.3},{"year":1981,"value":943.9,"rollingAvg":790.2},{"year":1982,"value":657.6,"rollingAvg":774.5},{"year":1983,"value":832.3,"rollingAvg":782.3},{"year":1984,"value":762.4,"rollingAvg":775.4},{"year":1985,"value":857.3,"rollingAvg":797.2},{"year":1986,"value":822.8,"rollingAvg":813.1},{"year":1987,"value":779.2,"rollingAvg":813.2},{"year":1988,"value":831.8,"rollingAvg":803.9},{"year":1989,"value":790.5,"rollingAvg":811.5},{"year":1990,"value":940.1,"rollingAvg":821.8},{"year":1991,"value":765.7,"rollingAvg":804},{"year":1992,"value":682.9,"rollingAvg":806.5},{"year":1993,"value":787.4,"rollingAvg":802},{"year":1994,"value":776.4,"rollingAvg":803.4},{"year":1995,"value":736.8,"rollingAvg":791.4},{"year":1996,"value":615.2,"rollingAvg":770.6},{"year":1997,"value":793.8,"rollingAvg":772.1},{"year":1998,"value":901.2,"rollingAvg":779},{"year":1999,"value":703.7,"rollingAvg":770.3},{"year":2000,"value":703.2,"rollingAvg":746.6},{"year":2001,"value":816.8,"rollingAvg":751.7},{"year":2002,"value":677.2,"rollingAvg":751.2},{"year":2003,"value":703.4,"rollingAvg":742.8},{"year":2004,"value":767.5,"rollingAvg":741.9},{"year":2005,"value":678.6,"rollingAvg":736.1},{"year":2006,"value":611.3,"rollingAvg":735.7},{"year":2007,"value":799.9,"rollingAvg":736.3},{"year":2008,"value":821,"rollingAvg":728.3},{"year":2009,"value":817.6,"rollingAvg":739.7},{"year":2010,"value":857.9,"rollingAvg":755.1},{"year":2011,"value":704.5,"rollingAvg":743.9},{"year":2012,"value":917.7,"rollingAvg":767.9},{"year":2013,"value":676.4,"rollingAvg":765.2},{"year":2014,"value":773.7,"rollingAvg":765.9},{"year":2015,"value":682.9,"rollingAvg":766.3},{"year":2016,"value":820.6,"rollingAvg":787.2},{"year":2017,"value":893.1,"rollingAvg":796.5},{"year":2018,"value":558,"rollingAvg":770.2},{"year":2019,"value":760.2,"rollingAvg":764.5},{"year":2020,"value":738.3,"rollingAvg":752.5},{"year":2021,"value":785.1,"rollingAvg":760.6},{"year":2022,"value":742.9,"rollingAvg":743.1},{"year":2023,"value":840,"rollingAvg":759.5},{"year":2024,"value":718.1,"rollingAvg":753.9}],"precipMonthly":{"source":"World Bank CKP (CRU TS 4.08)","sourceUrl":"https://climateknowledgeportal.worldbank.org/","units":"mm","yearRange":[1901,2023],"yearly":[{"year":1901,"value":574.6},{"year":1902,"value":694.3},{"year":1903,"value":739.7},{"year":1904,"value":652.5},{"year":1905,"value":659.9},{"year":1906,"value":699.4},{"year":1907,"value":574.9},{"year":1908,"value":625.8},{"year":1909,"value":541.5},{"year":1910,"value":642.4,"rollingAvg":640.5},{"year":1911,"value":588.9,"rollingAvg":641.93},{"year":1912,"value":691.1,"rollingAvg":641.61},{"year":1913,"value":651.4,"rollingAvg":632.78},{"year":1914,"value":574.8,"rollingAvg":625.01},{"year":1915,"value":634.5,"rollingAvg":622.47},{"year":1916,"value":708.8,"rollingAvg":623.41},{"year":1917,"value":639.7,"rollingAvg":629.89},{"year":1918,"value":557.8,"rollingAvg":623.09},{"year":1919,"value":590.2,"rollingAvg":627.96},{"year":1920,"value":513.5,"rollingAvg":615.07},{"year":1921,"value":618.4,"rollingAvg":618.02},{"year":1922,"value":648.9,"rollingAvg":613.8},{"year":1923,"value":733.5,"rollingAvg":622.01},{"year":1924,"value":651.5,"rollingAvg":629.68},{"year":1925,"value":756.1,"rollingAvg":641.84},{"year":1926,"value":704,"rollingAvg":641.36},{"year":1927,"value":705.8,"rollingAvg":647.97},{"year":1928,"value":746.9,"rollingAvg":666.88},{"year":1929,"value":604.1,"rollingAvg":668.27},{"year":1930,"value":725.4,"rollingAvg":689.46},{"year":1931,"value":639.5,"rollingAvg":691.57},{"year":1932,"value":665.4,"rollingAvg":693.22},{"year":1933,"value":625.6,"rollingAvg":682.43},{"year":1934,"value":614.9,"rollingAvg":678.77},{"year":1935,"value":743.2,"rollingAvg":677.48},{"year":1936,"value":660.8,"rollingAvg":673.16},{"year":1937,"value":655.8,"rollingAvg":668.16},{"year":1938,"value":597.4,"rollingAvg":653.21},{"year":1939,"value":554.3,"rollingAvg":648.23},{"year":1940,"value":664.6,"rollingAvg":642.15},{"year":1941,"value":545.6,"rollingAvg":632.76},{"year":1942,"value":576.5,"rollingAvg":623.87},{"year":1943,"value":658.1,"rollingAvg":627.12},{"year":1944,"value":610,"rollingAvg":626.63},{"year":1945,"value":721.9,"rollingAvg":624.5},{"year":1946,"value":606.4,"rollingAvg":619.06},{"year":1947,"value":563.4,"rollingAvg":609.82},{"year":1948,"value":675.3,"rollingAvg":617.61},{"year":1949,"value":646.6,"rollingAvg":626.84},{"year":1950,"value":783,"rollingAvg":638.68},{"year":1951,"value":519.3,"rollingAvg":636.05},{"year":1952,"value":746.3,"rollingAvg":653.03},{"year":1953,"value":550.9,"rollingAvg":642.31},{"year":1954,"value":712.9,"rollingAvg":652.6},{"year":1955,"value":595.9,"rollingAvg":640},{"year":1956,"value":686.7,"rollingAvg":648.03},{"year":1957,"value":721.9,"rollingAvg":663.88},{"year":1958,"value":625,"rollingAvg":658.85},{"year":1959,"value":558.7,"rollingAvg":650.06},{"year":1960,"value":703.3,"rollingAvg":642.09},{"year":1961,"value":614.2,"rollingAvg":651.58},{"year":1962,"value":713.7,"rollingAvg":648.32},{"year":1963,"value":566,"rollingAvg":649.83},{"year":1964,"value":514.7,"rollingAvg":630.01},{"year":1965,"value":581.4,"rollingAvg":628.56},{"year":1966,"value":707.2,"rollingAvg":630.61},{"year":1967,"value":668.6,"rollingAvg":625.28},{"year":1968,"value":583.7,"rollingAvg":621.15},{"year":1969,"value":550.9,"rollingAvg":620.37},{"year":1970,"value":685.2,"rollingAvg":618.56},{"year":1971,"value":547,"rollingAvg":611.84},{"year":1972,"value":647.4,"rollingAvg":605.21},{"year":1973,"value":621.2,"rollingAvg":610.73},{"year":1974,"value":697.8,"rollingAvg":629.04},{"year":1975,"value":519.7,"rollingAvg":622.87},{"year":1976,"value":518.3,"rollingAvg":603.98},{"year":1977,"value":671.8,"rollingAvg":604.3},{"year":1978,"value":757.9,"rollingAvg":621.72},{"year":1979,"value":644.4,"rollingAvg":631.07},{"year":1980,"value":743,"rollingAvg":636.85},{"year":1981,"value":777.3,"rollingAvg":659.88},{"year":1982,"value":555.8,"rollingAvg":650.72},{"year":1983,"value":686.4,"rollingAvg":657.24},{"year":1984,"value":604.5,"rollingAvg":647.91},{"year":1985,"value":738.3,"rollingAvg":669.77},{"year":1986,"value":706.9,"rollingAvg":688.63},{"year":1987,"value":693.6,"rollingAvg":690.81},{"year":1988,"value":666.5,"rollingAvg":681.67},{"year":1989,"value":682.2,"rollingAvg":685.45},{"year":1990,"value":827.3,"rollingAvg":693.88},{"year":1991,"value":656.4,"rollingAvg":681.79},{"year":1992,"value":620.1,"rollingAvg":688.22},{"year":1993,"value":661.2,"rollingAvg":685.7},{"year":1994,"value":665.2,"rollingAvg":691.77},{"year":1995,"value":679.5,"rollingAvg":685.89},{"year":1996,"value":564,"rollingAvg":671.6},{"year":1997,"value":719.9,"rollingAvg":674.23},{"year":1998,"value":771.3,"rollingAvg":684.71},{"year":1999,"value":624,"rollingAvg":678.89},{"year":2000,"value":644.3,"rollingAvg":660.59},{"year":2001,"value":766.5,"rollingAvg":671.6},{"year":2002,"value":570,"rollingAvg":666.59},{"year":2003,"value":648,"rollingAvg":665.27},{"year":2004,"value":691.3,"rollingAvg":667.88},{"year":2005,"value":606.1,"rollingAvg":660.54},{"year":2006,"value":609.1,"rollingAvg":665.05},{"year":2007,"value":703.7,"rollingAvg":663.43},{"year":2008,"value":699.8,"rollingAvg":656.28},{"year":2009,"value":743.4,"rollingAvg":668.22},{"year":2010,"value":800.5,"rollingAvg":683.84},{"year":2011,"value":650.1,"rollingAvg":672.2},{"year":2012,"value":801.5,"rollingAvg":695.35},{"year":2013,"value":659.5,"rollingAvg":696.5},{"year":2014,"value":671.9,"rollingAvg":694.56},{"year":2015,"value":577.7,"rollingAvg":691.72},{"year":2016,"value":739.1,"rollingAvg":704.72},{"year":2017,"value":821.6,"rollingAvg":716.51},{"year":2018,"value":578.4,"rollingAvg":704.37},{"year":2019,"value":668,"rollingAvg":696.83},{"year":2020,"value":657.1,"rollingAvg":682.49},{"year":2021,"value":690.1,"rollingAvg":686.49},{"year":2022,"value":637.3,"rollingAvg":670.07},{"year":2023,"value":723.3,"rollingAvg":676.45}],"monthlyComparison":[{"monthLabel":"Jan 2023","month":1,"year":2023,"recent":73.8,"historicAvg":38.68,"diff":35.12},{"monthLabel":"Feb 2023","month":2,"year":2023,"recent":35.7,"historicAvg":28.41,"diff":7.29},{"monthLabel":"Mar 2023","month":3,"year":2023,"recent":49.2,"historicAvg":34.45,"diff":14.75},{"monthLabel":"Apr 2023","month":4,"year":2023,"recent":30,"historicAvg":38.96,"diff":-8.96},{"monthLabel":"May 2023","month":5,"year":2023,"recent":14.4,"historicAvg":48.12,"diff":-33.72},{"monthLabel":"Jun 2023","month":6,"year":2023,"recent":35,"historicAvg":59.61,"diff":-24.61},{"monthLabel":"Jul 2023","month":7,"year":2023,"recent":80.5,"historicAvg":76.67,"diff":3.83},{"monthLabel":"Aug 2023","month":8,"year":2023,"recent":113.8,"historicAvg":77.17,"diff":36.63},{"monthLabel":"Sep 2023","month":9,"year":2023,"recent":44.4,"historicAvg":71.18,"diff":-26.78},{"monthLabel":"Oct 2023","month":10,"year":2023,"recent":111.3,"historicAvg":60.41,"diff":50.89},{"monthLabel":"Nov 2023","month":11,"year":2023,"recent":72,"historicAvg":63.8,"diff":8.2},{"monthLabel":"Dec 2023","month":12,"year":2023,"recent":63.2,"historicAvg":52.31,"diff":10.89}],"latestMonthStats":{"label":"Dec 2023","value":63.2,"diff":10.89,"rank":27,"total":123,"recordLabel":"Dec 2010","recordValue":82.5},"latestThreeMonthStats":{"label":"Oct–Dec 2023","value":82.17,"diff":23.33,"rank":6,"total":123,"recordLabel":"Oct–Dec 1981","recordValue":90.47}},"dataPoints":1023,"dateRange":"1941-01 to 2026-03","lastUpdated":"2026-04-v8","generatedAt":"2026-04-24T10:01:16.331Z"}