{"country":"Uzbekistan","code":"UZB","yearlyData":[{"year":1941,"avgTemp":13.37},{"year":1942,"avgTemp":15.07},{"year":1943,"avgTemp":13.85},{"year":1944,"avgTemp":12.73},{"year":1945,"avgTemp":14.25},{"year":1946,"avgTemp":12.61},{"year":1947,"avgTemp":13.73},{"year":1948,"avgTemp":13.99},{"year":1949,"avgTemp":13.22},{"year":1950,"avgTemp":11.13,"rollingAvg":13.4},{"year":1951,"avgTemp":11.04,"rollingAvg":13.16},{"year":1952,"avgTemp":11.79,"rollingAvg":12.83},{"year":1953,"avgTemp":12.23,"rollingAvg":12.67},{"year":1954,"avgTemp":12.56,"rollingAvg":12.66},{"year":1955,"avgTemp":11.4,"rollingAvg":12.37},{"year":1956,"avgTemp":13.55,"rollingAvg":12.46},{"year":1957,"avgTemp":12.26,"rollingAvg":12.32},{"year":1958,"avgTemp":11.87,"rollingAvg":12.11},{"year":1959,"avgTemp":12.8,"rollingAvg":12.06},{"year":1960,"avgTemp":11.56,"rollingAvg":12.11},{"year":1961,"avgTemp":11.96,"rollingAvg":12.2},{"year":1962,"avgTemp":13.37,"rollingAvg":12.36},{"year":1963,"avgTemp":12.63,"rollingAvg":12.4},{"year":1964,"avgTemp":13.39,"rollingAvg":12.48},{"year":1965,"avgTemp":11.8,"rollingAvg":12.52},{"year":1966,"avgTemp":12.96,"rollingAvg":12.46},{"year":1967,"avgTemp":13.41,"rollingAvg":12.58},{"year":1968,"avgTemp":12.53,"rollingAvg":12.64},{"year":1969,"avgTemp":12.4,"rollingAvg":12.6},{"year":1970,"avgTemp":10.73,"rollingAvg":12.52},{"year":1971,"avgTemp":12.71,"rollingAvg":12.59},{"year":1972,"avgTemp":13.35,"rollingAvg":12.59},{"year":1973,"avgTemp":10.97,"rollingAvg":12.43},{"year":1974,"avgTemp":12.73,"rollingAvg":12.36},{"year":1975,"avgTemp":11.63,"rollingAvg":12.34},{"year":1976,"avgTemp":12.93,"rollingAvg":12.34},{"year":1977,"avgTemp":11.62,"rollingAvg":12.16},{"year":1978,"avgTemp":12.81,"rollingAvg":12.19},{"year":1979,"avgTemp":12.37,"rollingAvg":12.18},{"year":1980,"avgTemp":13.21,"rollingAvg":12.43},{"year":1981,"avgTemp":12.64,"rollingAvg":12.43},{"year":1982,"avgTemp":13.15,"rollingAvg":12.41},{"year":1983,"avgTemp":12.04,"rollingAvg":12.51},{"year":1984,"avgTemp":13.8,"rollingAvg":12.62},{"year":1985,"avgTemp":11.49,"rollingAvg":12.61},{"year":1986,"avgTemp":12.68,"rollingAvg":12.58},{"year":1987,"avgTemp":12.83,"rollingAvg":12.7},{"year":1988,"avgTemp":12.48,"rollingAvg":12.67},{"year":1989,"avgTemp":13.23,"rollingAvg":12.76},{"year":1990,"avgTemp":12.72,"rollingAvg":12.71},{"year":1991,"avgTemp":13.31,"rollingAvg":12.77},{"year":1992,"avgTemp":12.74,"rollingAvg":12.73},{"year":1993,"avgTemp":12.44,"rollingAvg":12.77},{"year":1994,"avgTemp":11.56,"rollingAvg":12.55},{"year":1995,"avgTemp":12.32,"rollingAvg":12.63},{"year":1996,"avgTemp":13.65,"rollingAvg":12.73},{"year":1997,"avgTemp":12.09,"rollingAvg":12.65},{"year":1998,"avgTemp":13.64,"rollingAvg":12.77},{"year":1999,"avgTemp":13.01,"rollingAvg":12.75},{"year":2000,"avgTemp":13.7,"rollingAvg":12.85},{"year":2001,"avgTemp":13.64,"rollingAvg":12.88},{"year":2002,"avgTemp":13.77,"rollingAvg":12.98},{"year":2003,"avgTemp":13.62,"rollingAvg":13.1},{"year":2004,"avgTemp":12.84,"rollingAvg":13.23},{"year":2005,"avgTemp":14.28,"rollingAvg":13.42},{"year":2006,"avgTemp":13.94,"rollingAvg":13.45},{"year":2007,"avgTemp":13.62,"rollingAvg":13.61},{"year":2008,"avgTemp":13.88,"rollingAvg":13.63},{"year":2009,"avgTemp":13.2,"rollingAvg":13.65},{"year":2010,"avgTemp":13.58,"rollingAvg":13.64},{"year":2011,"avgTemp":14.19,"rollingAvg":13.69},{"year":2012,"avgTemp":13.03,"rollingAvg":13.62},{"year":2013,"avgTemp":13.14,"rollingAvg":13.57},{"year":2014,"avgTemp":14.37,"rollingAvg":13.72},{"year":2015,"avgTemp":12.62,"rollingAvg":13.56},{"year":2016,"avgTemp":14.07,"rollingAvg":13.57},{"year":2017,"avgTemp":14.54,"rollingAvg":13.66},{"year":2018,"avgTemp":13.71,"rollingAvg":13.65},{"year":2019,"avgTemp":13.45,"rollingAvg":13.67},{"year":2020,"avgTemp":14.45,"rollingAvg":13.76},{"year":2021,"avgTemp":13.47,"rollingAvg":13.68},{"year":2022,"avgTemp":14.48,"rollingAvg":13.83},{"year":2023,"avgTemp":14.4,"rollingAvg":13.96},{"year":2024,"avgTemp":15.27,"rollingAvg":14.05},{"year":2025,"avgTemp":14.38,"rollingAvg":14.22}],"monthlyComparison":[{"monthLabel":"Apr 2025","month":4,"year":2025,"recentTemp":17.63,"historicAvg":13.8,"diff":3.83},{"monthLabel":"May 2025","month":5,"year":2025,"recentTemp":20.78,"historicAvg":20.72,"diff":0.06},{"monthLabel":"Jun 2025","month":6,"year":2025,"recentTemp":29.2,"historicAvg":26.15,"diff":3.05},{"monthLabel":"Jul 2025","month":7,"year":2025,"recentTemp":29.33,"historicAvg":28.53,"diff":0.8},{"monthLabel":"Aug 2025","month":8,"year":2025,"recentTemp":27.92,"historicAvg":26.02,"diff":1.9},{"monthLabel":"Sep 2025","month":9,"year":2025,"recentTemp":19.85,"historicAvg":19.73,"diff":0.12},{"monthLabel":"Oct 2025","month":10,"year":2025,"recentTemp":13.11,"historicAvg":11.46,"diff":1.65},{"monthLabel":"Nov 2025","month":11,"year":2025,"recentTemp":6.37,"historicAvg":4.82,"diff":1.55},{"monthLabel":"Dec 2025","month":12,"year":2025,"recentTemp":-1.12,"historicAvg":-0.36,"diff":-0.76},{"monthLabel":"Jan 2026","month":1,"year":2026,"recentTemp":-0.11,"historicAvg":-3.36,"diff":3.25},{"monthLabel":"Feb 2026","month":2,"year":2026,"recentTemp":0.61,"historicAvg":-1.8,"diff":2.41},{"monthLabel":"Mar 2026","month":3,"year":2026,"recentTemp":8.95,"historicAvg":4.92,"diff":4.03}],"latestMonthStats":{"label":"Mar 2026","value":8.95,"diff":4.03,"rank":13,"total":86,"recordLabel":"Mar 2024","recordValue":12.9},"latestThreeMonthStats":{"label":"Jan–Mar 2026","value":3.15,"diff":3.23,"rank":15,"total":86,"recordLabel":"Jan–Mar 2017","recordValue":5.93},"monthlyAll":[{"year":1941,"month":1,"value":-4.83},{"year":1941,"month":2,"value":-3.62},{"year":1941,"month":3,"value":2.8},{"year":1941,"month":4,"value":15.69},{"year":1941,"month":5,"value":19.46},{"year":1941,"month":6,"value":27.86},{"year":1941,"month":7,"value":30.85},{"year":1941,"month":8,"value":28.49},{"year":1941,"month":9,"value":21.78},{"year":1941,"month":10,"value":13.22},{"year":1941,"month":11,"value":5.9},{"year":1941,"month":12,"value":2.81},{"year":1942,"month":1,"value":-2.61},{"year":1942,"month":2,"value":3.14},{"year":1942,"month":3,"value":8.82},{"year":1942,"month":4,"value":17.08},{"year":1942,"month":5,"value":24.66},{"year":1942,"month":6,"value":30.39},{"year":1942,"month":7,"value":28.99},{"year":1942,"month":8,"value":28.54},{"year":1942,"month":9,"value":22.29},{"year":1942,"month":10,"value":14.77},{"year":1942,"month":11,"value":4.46},{"year":1942,"month":12,"value":0.34},{"year":1943,"month":1,"value":-0.26},{"year":1943,"month":2,"value":-2.84},{"year":1943,"month":3,"value":5.4},{"year":1943,"month":4,"value":13.77},{"year":1943,"month":5,"value":23.16},{"year":1943,"month":6,"value":29.23},{"year":1943,"month":7,"value":31.22},{"year":1943,"month":8,"value":27.5},{"year":1943,"month":9,"value":20.5},{"year":1943,"month":10,"value":13.32},{"year":1943,"month":11,"value":5.86},{"year":1943,"month":12,"value":-0.63},{"year":1944,"month":1,"value":-4.11},{"year":1944,"month":2,"value":-4.25},{"year":1944,"month":3,"value":1.52},{"year":1944,"month":4,"value":13.86},{"year":1944,"month":5,"value":23.07},{"year":1944,"month":6,"value":26.65},{"year":1944,"month":7,"value":31.63},{"year":1944,"month":8,"value":28.2},{"year":1944,"month":9,"value":20.69},{"year":1944,"month":10,"value":12.07},{"year":1944,"month":11,"value":3.32},{"year":1944,"month":12,"value":0.05},{"year":1945,"month":1,"value":0.49},{"year":1945,"month":2,"value":4.25},{"year":1945,"month":3,"value":12.14},{"year":1945,"month":4,"value":15.35},{"year":1945,"month":5,"value":23.69},{"year":1945,"month":6,"value":27.04},{"year":1945,"month":7,"value":31.94},{"year":1945,"month":8,"value":27.37},{"year":1945,"month":9,"value":21.04},{"year":1945,"month":10,"value":11.68},{"year":1945,"month":11,"value":3.29},{"year":1945,"month":12,"value":-7.27},{"year":1946,"month":1,"value":-4.84},{"year":1946,"month":2,"value":-6.58},{"year":1946,"month":3,"value":3.2},{"year":1946,"month":4,"value":14.02},{"year":1946,"month":5,"value":20.51},{"year":1946,"month":6,"value":27.2},{"year":1946,"month":7,"value":29.27},{"year":1946,"month":8,"value":30.55},{"year":1946,"month":9,"value":21.61},{"year":1946,"month":10,"value":14.64},{"year":1946,"month":11,"value":2.57},{"year":1946,"month":12,"value":-0.82},{"year":1947,"month":1,"value":-2.72},{"year":1947,"month":2,"value":4.25},{"year":1947,"month":3,"value":6.77},{"year":1947,"month":4,"value":15.03},{"year":1947,"month":5,"value":24.95},{"year":1947,"month":6,"value":27.28},{"year":1947,"month":7,"value":28.91},{"year":1947,"month":8,"value":27.5},{"year":1947,"month":9,"value":23.07},{"year":1947,"month":10,"value":13.45},{"year":1947,"month":11,"value":2.43},{"year":1947,"month":12,"value":-6.14},{"year":1948,"month":1,"value":-2.91},{"year":1948,"month":2,"value":-0.47},{"year":1948,"month":3,"value":10.14},{"year":1948,"month":4,"value":15.78},{"year":1948,"month":5,"value":21.05},{"year":1948,"month":6,"value":25.81},{"year":1948,"month":7,"value":28.98},{"year":1948,"month":8,"value":28.4},{"year":1948,"month":9,"value":20.97},{"year":1948,"month":10,"value":12.63},{"year":1948,"month":11,"value":8.17},{"year":1948,"month":12,"value":-0.63},{"year":1949,"month":1,"value":0.85},{"year":1949,"month":2,"value":1.81},{"year":1949,"month":3,"value":4.47},{"year":1949,"month":4,"value":11.62},{"year":1949,"month":5,"value":22.59},{"year":1949,"month":6,"value":27.36},{"year":1949,"month":7,"value":29.99},{"year":1949,"month":8,"value":27.66},{"year":1949,"month":9,"value":19.63},{"year":1949,"month":10,"value":12.65},{"year":1949,"month":11,"value":4.51},{"year":1949,"month":12,"value":-4.47},{"year":1950,"month":1,"value":-4.81},{"year":1950,"month":2,"value":-2.36},{"year":1950,"month":3,"value":1.46},{"year":1950,"month":4,"value":12.34},{"year":1950,"month":5,"value":20.57},{"year":1950,"month":6,"value":27.07},{"year":1950,"month":7,"value":28.47},{"year":1950,"month":8,"value":25.18},{"year":1950,"month":9,"value":17.59},{"year":1950,"month":10,"value":8.16},{"year":1950,"month":11,"value":1.69},{"year":1950,"month":12,"value":-1.77},{"year":1951,"month":1,"value":-6.41},{"year":1951,"month":2,"value":-4.79},{"year":1951,"month":3,"value":5.64},{"year":1951,"month":4,"value":13.24},{"year":1951,"month":5,"value":22.43},{"year":1951,"month":6,"value":25.91},{"year":1951,"month":7,"value":27.67},{"year":1951,"month":8,"value":25.82},{"year":1951,"month":9,"value":19.77},{"year":1951,"month":10,"value":11.74},{"year":1951,"month":11,"value":-1.16},{"year":1951,"month":12,"value":-7.33},{"year":1952,"month":1,"value":-6.05},{"year":1952,"month":2,"value":-8.53},{"year":1952,"month":3,"value":3.9},{"year":1952,"month":4,"value":15.72},{"year":1952,"month":5,"value":22.04},{"year":1952,"month":6,"value":24.21},{"year":1952,"month":7,"value":28.22},{"year":1952,"month":8,"value":25.67},{"year":1952,"month":9,"value":20.31},{"year":1952,"month":10,"value":11.09},{"year":1952,"month":11,"value":2.97},{"year":1952,"month":12,"value":1.9},{"year":1953,"month":1,"value":-2.07},{"year":1953,"month":2,"value":2.45},{"year":1953,"month":3,"value":4.22},{"year":1953,"month":4,"value":12.7},{"year":1953,"month":5,"value":20.68},{"year":1953,"month":6,"value":25.26},{"year":1953,"month":7,"value":29.39},{"year":1953,"month":8,"value":27.14},{"year":1953,"month":9,"value":19.9},{"year":1953,"month":10,"value":12.3},{"year":1953,"month":11,"value":-0.38},{"year":1953,"month":12,"value":-4.81},{"year":1954,"month":1,"value":-0.72},{"year":1954,"month":2,"value":4.48},{"year":1954,"month":3,"value":4.41},{"year":1954,"month":4,"value":12.92},{"year":1954,"month":5,"value":21.11},{"year":1954,"month":6,"value":25.59},{"year":1954,"month":7,"value":28.74},{"year":1954,"month":8,"value":26.67},{"year":1954,"month":9,"value":19.91},{"year":1954,"month":10,"value":9.01},{"year":1954,"month":11,"value":0.94},{"year":1954,"month":12,"value":-2.29},{"year":1955,"month":1,"value":-3.6},{"year":1955,"month":2,"value":-5.12},{"year":1955,"month":3,"value":-0.16},{"year":1955,"month":4,"value":12.9},{"year":1955,"month":5,"value":20.11},{"year":1955,"month":6,"value":23.96},{"year":1955,"month":7,"value":28.6},{"year":1955,"month":8,"value":25.75},{"year":1955,"month":9,"value":20.24},{"year":1955,"month":10,"value":13.52},{"year":1955,"month":11,"value":3.11},{"year":1955,"month":12,"value":-2.56},{"year":1956,"month":1,"value":-1.36},{"year":1956,"month":2,"value":3.39},{"year":1956,"month":3,"value":5.29},{"year":1956,"month":4,"value":12.11},{"year":1956,"month":5,"value":21.45},{"year":1956,"month":6,"value":26.72},{"year":1956,"month":7,"value":28.64},{"year":1956,"month":8,"value":27.42},{"year":1956,"month":9,"value":20.33},{"year":1956,"month":10,"value":11.5},{"year":1956,"month":11,"value":6.05},{"year":1956,"month":12,"value":1},{"year":1957,"month":1,"value":-5.07},{"year":1957,"month":2,"value":-2.84},{"year":1957,"month":3,"value":3.09},{"year":1957,"month":4,"value":15.21},{"year":1957,"month":5,"value":20.4},{"year":1957,"month":6,"value":24.69},{"year":1957,"month":7,"value":29.68},{"year":1957,"month":8,"value":26.75},{"year":1957,"month":9,"value":19.05},{"year":1957,"month":10,"value":12.1},{"year":1957,"month":11,"value":6.56},{"year":1957,"month":12,"value":-2.51},{"year":1958,"month":1,"value":-7.27},{"year":1958,"month":2,"value":-2.73},{"year":1958,"month":3,"value":5.37},{"year":1958,"month":4,"value":12.36},{"year":1958,"month":5,"value":21.26},{"year":1958,"month":6,"value":25.4},{"year":1958,"month":7,"value":26.05},{"year":1958,"month":8,"value":25.39},{"year":1958,"month":9,"value":21.43},{"year":1958,"month":10,"value":11.47},{"year":1958,"month":11,"value":2.88},{"year":1958,"month":12,"value":0.8},{"year":1959,"month":1,"value":1.45},{"year":1959,"month":2,"value":3.3},{"year":1959,"month":3,"value":7.4},{"year":1959,"month":4,"value":12.31},{"year":1959,"month":5,"value":18.95},{"year":1959,"month":6,"value":26.63},{"year":1959,"month":7,"value":28.47},{"year":1959,"month":8,"value":25.33},{"year":1959,"month":9,"value":18.21},{"year":1959,"month":10,"value":10.88},{"year":1959,"month":11,"value":1.02},{"year":1959,"month":12,"value":-0.34},{"year":1960,"month":1,"value":-3.03},{"year":1960,"month":2,"value":-2.27},{"year":1960,"month":3,"value":3.57},{"year":1960,"month":4,"value":15.42},{"year":1960,"month":5,"value":20.07},{"year":1960,"month":6,"value":25.68},{"year":1960,"month":7,"value":26.67},{"year":1960,"month":8,"value":26.4},{"year":1960,"month":9,"value":21.57},{"year":1960,"month":10,"value":10.8},{"year":1960,"month":11,"value":0.14},{"year":1960,"month":12,"value":-6.32},{"year":1961,"month":1,"value":-0.18},{"year":1961,"month":2,"value":2.52},{"year":1961,"month":3,"value":-0.32},{"year":1961,"month":4,"value":12.19},{"year":1961,"month":5,"value":17.62},{"year":1961,"month":6,"value":26.69},{"year":1961,"month":7,"value":26.65},{"year":1961,"month":8,"value":26.02},{"year":1961,"month":9,"value":19.1},{"year":1961,"month":10,"value":12.18},{"year":1961,"month":11,"value":2.81},{"year":1961,"month":12,"value":-1.77},{"year":1962,"month":1,"value":-1.22},{"year":1962,"month":2,"value":-0.65},{"year":1962,"month":3,"value":6.41},{"year":1962,"month":4,"value":14.11},{"year":1962,"month":5,"value":24.66},{"year":1962,"month":6,"value":26.14},{"year":1962,"month":7,"value":28.33},{"year":1962,"month":8,"value":26.53},{"year":1962,"month":9,"value":19.28},{"year":1962,"month":10,"value":9.66},{"year":1962,"month":11,"value":5.62},{"year":1962,"month":12,"value":1.6},{"year":1963,"month":1,"value":-2.99},{"year":1963,"month":2,"value":1.5},{"year":1963,"month":3,"value":8.94},{"year":1963,"month":4,"value":13.02},{"year":1963,"month":5,"value":20.31},{"year":1963,"month":6,"value":24.93},{"year":1963,"month":7,"value":29.82},{"year":1963,"month":8,"value":25.54},{"year":1963,"month":9,"value":18.69},{"year":1963,"month":10,"value":11.67},{"year":1963,"month":11,"value":1.56},{"year":1963,"month":12,"value":-1.43},{"year":1964,"month":1,"value":0.5},{"year":1964,"month":2,"value":4.03},{"year":1964,"month":3,"value":6.1},{"year":1964,"month":4,"value":14.39},{"year":1964,"month":5,"value":20.94},{"year":1964,"month":6,"value":25.63},{"year":1964,"month":7,"value":27.65},{"year":1964,"month":8,"value":24.73},{"year":1964,"month":9,"value":19.31},{"year":1964,"month":10,"value":13.59},{"year":1964,"month":11,"value":5.14},{"year":1964,"month":12,"value":-1.39},{"year":1965,"month":1,"value":-6.51},{"year":1965,"month":2,"value":-1.26},{"year":1965,"month":3,"value":5.66},{"year":1965,"month":4,"value":11.98},{"year":1965,"month":5,"value":20.68},{"year":1965,"month":6,"value":25.42},{"year":1965,"month":7,"value":28.04},{"year":1965,"month":8,"value":25.88},{"year":1965,"month":9,"value":19.6},{"year":1965,"month":10,"value":9.31},{"year":1965,"month":11,"value":6.15},{"year":1965,"month":12,"value":-3.4},{"year":1966,"month":1,"value":-3.62},{"year":1966,"month":2,"value":-1.75},{"year":1966,"month":3,"value":5.62},{"year":1966,"month":4,"value":12.75},{"year":1966,"month":5,"value":22},{"year":1966,"month":6,"value":26.25},{"year":1966,"month":7,"value":28.83},{"year":1966,"month":8,"value":25.89},{"year":1966,"month":9,"value":19.57},{"year":1966,"month":10,"value":11.71},{"year":1966,"month":11,"value":6.64},{"year":1966,"month":12,"value":1.64},{"year":1967,"month":1,"value":1.22},{"year":1967,"month":2,"value":3.68},{"year":1967,"month":3,"value":6.8},{"year":1967,"month":4,"value":14.41},{"year":1967,"month":5,"value":19.86},{"year":1967,"month":6,"value":27.66},{"year":1967,"month":7,"value":29.1},{"year":1967,"month":8,"value":27.62},{"year":1967,"month":9,"value":19.91},{"year":1967,"month":10,"value":10.56},{"year":1967,"month":11,"value":2.83},{"year":1967,"month":12,"value":-2.74},{"year":1968,"month":1,"value":-3.31},{"year":1968,"month":2,"value":-3.22},{"year":1968,"month":3,"value":5.11},{"year":1968,"month":4,"value":13.81},{"year":1968,"month":5,"value":20.49},{"year":1968,"month":6,"value":25.45},{"year":1968,"month":7,"value":27.72},{"year":1968,"month":8,"value":26.27},{"year":1968,"month":9,"value":18.85},{"year":1968,"month":10,"value":11.52},{"year":1968,"month":11,"value":6.15},{"year":1968,"month":12,"value":1.55},{"year":1969,"month":1,"value":-0.36},{"year":1969,"month":2,"value":-1.72},{"year":1969,"month":3,"value":7.04},{"year":1969,"month":4,"value":12},{"year":1969,"month":5,"value":21.23},{"year":1969,"month":6,"value":25.34},{"year":1969,"month":7,"value":27.39},{"year":1969,"month":8,"value":25.84},{"year":1969,"month":9,"value":19.56},{"year":1969,"month":10,"value":10.75},{"year":1969,"month":11,"value":4.4},{"year":1969,"month":12,"value":-2.62},{"year":1970,"month":1,"value":-12.24},{"year":1970,"month":2,"value":-10.84},{"year":1970,"month":3,"value":2.85},{"year":1970,"month":4,"value":12.38},{"year":1970,"month":5,"value":19.08},{"year":1970,"month":6,"value":26.36},{"year":1970,"month":7,"value":26.8},{"year":1970,"month":8,"value":25.01},{"year":1970,"month":9,"value":19.57},{"year":1970,"month":10,"value":11.83},{"year":1970,"month":11,"value":4.72},{"year":1970,"month":12,"value":3.26},{"year":1971,"month":1,"value":-4.87},{"year":1971,"month":2,"value":1.98},{"year":1971,"month":3,"value":5.36},{"year":1971,"month":4,"value":15.14},{"year":1971,"month":5,"value":21.98},{"year":1971,"month":6,"value":25.34},{"year":1971,"month":7,"value":27.42},{"year":1971,"month":8,"value":26.13},{"year":1971,"month":9,"value":19.66},{"year":1971,"month":10,"value":12.17},{"year":1971,"month":11,"value":5.15},{"year":1971,"month":12,"value":-2.91},{"year":1972,"month":1,"value":-4.91},{"year":1972,"month":2,"value":-1.13},{"year":1972,"month":3,"value":6.73},{"year":1972,"month":4,"value":12.39},{"year":1972,"month":5,"value":20.99},{"year":1972,"month":6,"value":26.06},{"year":1972,"month":7,"value":28.48},{"year":1972,"month":8,"value":25.2},{"year":1972,"month":9,"value":21.19},{"year":1972,"month":10,"value":13.1},{"year":1972,"month":11,"value":8.25},{"year":1972,"month":12,"value":3.81},{"year":1973,"month":1,"value":-9.2},{"year":1973,"month":2,"value":-9.41},{"year":1973,"month":3,"value":1.94},{"year":1973,"month":4,"value":14.23},{"year":1973,"month":5,"value":20.09},{"year":1973,"month":6,"value":25.83},{"year":1973,"month":7,"value":26.65},{"year":1973,"month":8,"value":24.47},{"year":1973,"month":9,"value":19.8},{"year":1973,"month":10,"value":12.8},{"year":1973,"month":11,"value":7.16},{"year":1973,"month":12,"value":-2.7},{"year":1974,"month":1,"value":-6.62},{"year":1974,"month":2,"value":0.64},{"year":1974,"month":3,"value":5.22},{"year":1974,"month":4,"value":14.24},{"year":1974,"month":5,"value":20.47},{"year":1974,"month":6,"value":27.28},{"year":1974,"month":7,"value":28.72},{"year":1974,"month":8,"value":26.65},{"year":1974,"month":9,"value":17.18},{"year":1974,"month":10,"value":11.94},{"year":1974,"month":11,"value":6.53},{"year":1974,"month":12,"value":0.49},{"year":1975,"month":1,"value":-7.56},{"year":1975,"month":2,"value":-7.41},{"year":1975,"month":3,"value":4.71},{"year":1975,"month":4,"value":12.84},{"year":1975,"month":5,"value":22.38},{"year":1975,"month":6,"value":26.18},{"year":1975,"month":7,"value":28.47},{"year":1975,"month":8,"value":24.49},{"year":1975,"month":9,"value":19.65},{"year":1975,"month":10,"value":13.13},{"year":1975,"month":11,"value":5.99},{"year":1975,"month":12,"value":-3.36},{"year":1976,"month":1,"value":-1.71},{"year":1976,"month":2,"value":-2.52},{"year":1976,"month":3,"value":6.16},{"year":1976,"month":4,"value":15.67},{"year":1976,"month":5,"value":21.1},{"year":1976,"month":6,"value":27.03},{"year":1976,"month":7,"value":30.2},{"year":1976,"month":8,"value":26.59},{"year":1976,"month":9,"value":20.83},{"year":1976,"month":10,"value":10.74},{"year":1976,"month":11,"value":1.38},{"year":1976,"month":12,"value":-0.27},{"year":1977,"month":1,"value":1.16},{"year":1977,"month":2,"value":-5.46},{"year":1977,"month":3,"value":1.22},{"year":1977,"month":4,"value":13.85},{"year":1977,"month":5,"value":21.36},{"year":1977,"month":6,"value":26.37},{"year":1977,"month":7,"value":28.68},{"year":1977,"month":8,"value":28.12},{"year":1977,"month":9,"value":19.35},{"year":1977,"month":10,"value":8.27},{"year":1977,"month":11,"value":0.95},{"year":1977,"month":12,"value":-4.46},{"year":1978,"month":1,"value":-11.82},{"year":1978,"month":2,"value":-2.77},{"year":1978,"month":3,"value":8.57},{"year":1978,"month":4,"value":16.96},{"year":1978,"month":5,"value":22.5},{"year":1978,"month":6,"value":28.99},{"year":1978,"month":7,"value":28.53},{"year":1978,"month":8,"value":25.59},{"year":1978,"month":9,"value":20.67},{"year":1978,"month":10,"value":10.35},{"year":1978,"month":11,"value":6.72},{"year":1978,"month":12,"value":-0.59},{"year":1979,"month":1,"value":-3.09},{"year":1979,"month":2,"value":-4.56},{"year":1979,"month":3,"value":4.66},{"year":1979,"month":4,"value":14.04},{"year":1979,"month":5,"value":18.89},{"year":1979,"month":6,"value":25.21},{"year":1979,"month":7,"value":28.74},{"year":1979,"month":8,"value":24.71},{"year":1979,"month":9,"value":22.03},{"year":1979,"month":10,"value":12.05},{"year":1979,"month":11,"value":3.58},{"year":1979,"month":12,"value":2.22},{"year":1980,"month":1,"value":-3.63},{"year":1980,"month":2,"value":0.86},{"year":1980,"month":3,"value":5.59},{"year":1980,"month":4,"value":13.43},{"year":1980,"month":5,"value":18.51},{"year":1980,"month":6,"value":24.5},{"year":1980,"month":7,"value":29.54},{"year":1980,"month":8,"value":26.35},{"year":1980,"month":9,"value":21.19},{"year":1980,"month":10,"value":14.76},{"year":1980,"month":11,"value":4.55},{"year":1980,"month":12,"value":2.81},{"year":1981,"month":1,"value":-5.3},{"year":1981,"month":2,"value":-5.04},{"year":1981,"month":3,"value":3.07},{"year":1981,"month":4,"value":15.28},{"year":1981,"month":5,"value":21.93},{"year":1981,"month":6,"value":26.39},{"year":1981,"month":7,"value":29.59},{"year":1981,"month":8,"value":25.26},{"year":1981,"month":9,"value":19.31},{"year":1981,"month":10,"value":11.17},{"year":1981,"month":11,"value":7.76},{"year":1981,"month":12,"value":2.32},{"year":1982,"month":1,"value":0.79},{"year":1982,"month":2,"value":0.68},{"year":1982,"month":3,"value":7.44},{"year":1982,"month":4,"value":12.63},{"year":1982,"month":5,"value":18.94},{"year":1982,"month":6,"value":24.79},{"year":1982,"month":7,"value":28.61},{"year":1982,"month":8,"value":26.33},{"year":1982,"month":9,"value":20.16},{"year":1982,"month":10,"value":10.84},{"year":1982,"month":11,"value":5.94},{"year":1982,"month":12,"value":0.7},{"year":1983,"month":1,"value":-3.13},{"year":1983,"month":2,"value":-2.29},{"year":1983,"month":3,"value":3.47},{"year":1983,"month":4,"value":16.06},{"year":1983,"month":5,"value":21.75},{"year":1983,"month":6,"value":24.89},{"year":1983,"month":7,"value":27.66},{"year":1983,"month":8,"value":25.34},{"year":1983,"month":9,"value":19.12},{"year":1983,"month":10,"value":11.29},{"year":1983,"month":11,"value":1.6},{"year":1983,"month":12,"value":-1.28},{"year":1984,"month":1,"value":-0.76},{"year":1984,"month":2,"value":2.94},{"year":1984,"month":3,"value":4.82},{"year":1984,"month":4,"value":15.97},{"year":1984,"month":5,"value":20.67},{"year":1984,"month":6,"value":26.08},{"year":1984,"month":7,"value":30.83},{"year":1984,"month":8,"value":27.26},{"year":1984,"month":9,"value":19.55},{"year":1984,"month":10,"value":11.65},{"year":1984,"month":11,"value":6.81},{"year":1984,"month":12,"value":-0.24},{"year":1985,"month":1,"value":-3.24},{"year":1985,"month":2,"value":-8.56},{"year":1985,"month":3,"value":4.25},{"year":1985,"month":4,"value":13.08},{"year":1985,"month":5,"value":20.79},{"year":1985,"month":6,"value":26.54},{"year":1985,"month":7,"value":30.71},{"year":1985,"month":8,"value":28.29},{"year":1985,"month":9,"value":19.21},{"year":1985,"month":10,"value":11.97},{"year":1985,"month":11,"value":4.54},{"year":1985,"month":12,"value":-9.76},{"year":1986,"month":1,"value":-3.92},{"year":1986,"month":2,"value":1.97},{"year":1986,"month":3,"value":2.1},{"year":1986,"month":4,"value":15.52},{"year":1986,"month":5,"value":21.13},{"year":1986,"month":6,"value":27.45},{"year":1986,"month":7,"value":28.43},{"year":1986,"month":8,"value":25.51},{"year":1986,"month":9,"value":20.03},{"year":1986,"month":10,"value":10.08},{"year":1986,"month":11,"value":3.26},{"year":1986,"month":12,"value":0.59},{"year":1987,"month":1,"value":0.25},{"year":1987,"month":2,"value":-0.16},{"year":1987,"month":3,"value":1.84},{"year":1987,"month":4,"value":13.96},{"year":1987,"month":5,"value":21.27},{"year":1987,"month":6,"value":25.92},{"year":1987,"month":7,"value":28.48},{"year":1987,"month":8,"value":25.66},{"year":1987,"month":9,"value":21.52},{"year":1987,"month":10,"value":11.87},{"year":1987,"month":11,"value":3.54},{"year":1987,"month":12,"value":-0.16},{"year":1988,"month":1,"value":0.46},{"year":1988,"month":2,"value":0},{"year":1988,"month":3,"value":4.6},{"year":1988,"month":4,"value":10.68},{"year":1988,"month":5,"value":21.44},{"year":1988,"month":6,"value":25.58},{"year":1988,"month":7,"value":27.41},{"year":1988,"month":8,"value":27.38},{"year":1988,"month":9,"value":19.19},{"year":1988,"month":10,"value":7.8},{"year":1988,"month":11,"value":3.48},{"year":1988,"month":12,"value":1.71},{"year":1989,"month":1,"value":-1.49},{"year":1989,"month":2,"value":-4.11},{"year":1989,"month":3,"value":5.25},{"year":1989,"month":4,"value":15.57},{"year":1989,"month":5,"value":19.28},{"year":1989,"month":6,"value":28.05},{"year":1989,"month":7,"value":29.06},{"year":1989,"month":8,"value":25.58},{"year":1989,"month":9,"value":19.87},{"year":1989,"month":10,"value":11.65},{"year":1989,"month":11,"value":6.98},{"year":1989,"month":12,"value":3.12},{"year":1990,"month":1,"value":-3.56},{"year":1990,"month":2,"value":-1.98},{"year":1990,"month":3,"value":6.26},{"year":1990,"month":4,"value":11.36},{"year":1990,"month":5,"value":19.26},{"year":1990,"month":6,"value":26.27},{"year":1990,"month":7,"value":29.49},{"year":1990,"month":8,"value":26.44},{"year":1990,"month":9,"value":18.83},{"year":1990,"month":10,"value":13.31},{"year":1990,"month":11,"value":4.44},{"year":1990,"month":12,"value":2.54},{"year":1991,"month":1,"value":-3.53},{"year":1991,"month":2,"value":0.22},{"year":1991,"month":3,"value":7.42},{"year":1991,"month":4,"value":13.96},{"year":1991,"month":5,"value":21.19},{"year":1991,"month":6,"value":28.28},{"year":1991,"month":7,"value":28.17},{"year":1991,"month":8,"value":26.5},{"year":1991,"month":9,"value":21.76},{"year":1991,"month":10,"value":11.44},{"year":1991,"month":11,"value":6.53},{"year":1991,"month":12,"value":-2.23},{"year":1992,"month":1,"value":-3.48},{"year":1992,"month":2,"value":-1.76},{"year":1992,"month":3,"value":4.45},{"year":1992,"month":4,"value":15.2},{"year":1992,"month":5,"value":19.49},{"year":1992,"month":6,"value":26.05},{"year":1992,"month":7,"value":28.67},{"year":1992,"month":8,"value":25.65},{"year":1992,"month":9,"value":19.94},{"year":1992,"month":10,"value":13.73},{"year":1992,"month":11,"value":4.83},{"year":1992,"month":12,"value":0.07},{"year":1993,"month":1,"value":-0.82},{"year":1993,"month":2,"value":1.34},{"year":1993,"month":3,"value":3.02},{"year":1993,"month":4,"value":13.28},{"year":1993,"month":5,"value":17.57},{"year":1993,"month":6,"value":25.16},{"year":1993,"month":7,"value":27.77},{"year":1993,"month":8,"value":24.03},{"year":1993,"month":9,"value":18.6},{"year":1993,"month":10,"value":10.75},{"year":1993,"month":11,"value":6.85},{"year":1993,"month":12,"value":1.73},{"year":1994,"month":1,"value":-2.39},{"year":1994,"month":2,"value":-0.82},{"year":1994,"month":3,"value":4.15},{"year":1994,"month":4,"value":13.6},{"year":1994,"month":5,"value":18.64},{"year":1994,"month":6,"value":26.37},{"year":1994,"month":7,"value":28.33},{"year":1994,"month":8,"value":25.42},{"year":1994,"month":9,"value":19.08},{"year":1994,"month":10,"value":10.17},{"year":1994,"month":11,"value":-0.77},{"year":1994,"month":12,"value":-3.06},{"year":1995,"month":1,"value":-3.38},{"year":1995,"month":2,"value":-4.95},{"year":1995,"month":3,"value":5.03},{"year":1995,"month":4,"value":11.96},{"year":1995,"month":5,"value":21.02},{"year":1995,"month":6,"value":26.7},{"year":1995,"month":7,"value":27.42},{"year":1995,"month":8,"value":27.15},{"year":1995,"month":9,"value":17.95},{"year":1995,"month":10,"value":12.51},{"year":1995,"month":11,"value":7.64},{"year":1995,"month":12,"value":-1.24},{"year":1996,"month":1,"value":-1.46},{"year":1996,"month":2,"value":1.47},{"year":1996,"month":3,"value":5.54},{"year":1996,"month":4,"value":16.39},{"year":1996,"month":5,"value":20.84},{"year":1996,"month":6,"value":26.73},{"year":1996,"month":7,"value":29.32},{"year":1996,"month":8,"value":27.22},{"year":1996,"month":9,"value":20.06},{"year":1996,"month":10,"value":11.46},{"year":1996,"month":11,"value":8.14},{"year":1996,"month":12,"value":-1.93},{"year":1997,"month":1,"value":-5.34},{"year":1997,"month":2,"value":-2.91},{"year":1997,"month":3,"value":2.59},{"year":1997,"month":4,"value":11.6},{"year":1997,"month":5,"value":20.8},{"year":1997,"month":6,"value":26.72},{"year":1997,"month":7,"value":28.94},{"year":1997,"month":8,"value":25.45},{"year":1997,"month":9,"value":20.54},{"year":1997,"month":10,"value":11.52},{"year":1997,"month":11,"value":3.25},{"year":1997,"month":12,"value":1.95},{"year":1998,"month":1,"value":-0.64},{"year":1998,"month":2,"value":-0.89},{"year":1998,"month":3,"value":7.04},{"year":1998,"month":4,"value":16},{"year":1998,"month":5,"value":20.93},{"year":1998,"month":6,"value":27.8},{"year":1998,"month":7,"value":29.4},{"year":1998,"month":8,"value":26.39},{"year":1998,"month":9,"value":20.26},{"year":1998,"month":10,"value":16.7},{"year":1998,"month":11,"value":2.26},{"year":1998,"month":12,"value":-1.56},{"year":1999,"month":1,"value":-4.24},{"year":1999,"month":2,"value":-1.71},{"year":1999,"month":3,"value":3.83},{"year":1999,"month":4,"value":14.88},{"year":1999,"month":5,"value":19.92},{"year":1999,"month":6,"value":27.23},{"year":1999,"month":7,"value":29.57},{"year":1999,"month":8,"value":27.56},{"year":1999,"month":9,"value":20.62},{"year":1999,"month":10,"value":11.77},{"year":1999,"month":11,"value":5.42},{"year":1999,"month":12,"value":1.25},{"year":2000,"month":1,"value":-0.68},{"year":2000,"month":2,"value":5.55},{"year":2000,"month":3,"value":4.4},{"year":2000,"month":4,"value":13.44},{"year":2000,"month":5,"value":20.28},{"year":2000,"month":6,"value":25.59},{"year":2000,"month":7,"value":27.48},{"year":2000,"month":8,"value":28.79},{"year":2000,"month":9,"value":20.03},{"year":2000,"month":10,"value":14.41},{"year":2000,"month":11,"value":3.35},{"year":2000,"month":12,"value":1.75},{"year":2001,"month":1,"value":-1.05},{"year":2001,"month":2,"value":1.31},{"year":2001,"month":3,"value":6.32},{"year":2001,"month":4,"value":18.62},{"year":2001,"month":5,"value":21.5},{"year":2001,"month":6,"value":26.19},{"year":2001,"month":7,"value":28.59},{"year":2001,"month":8,"value":28.13},{"year":2001,"month":9,"value":20.14},{"year":2001,"month":10,"value":9.43},{"year":2001,"month":11,"value":2.75},{"year":2001,"month":12,"value":1.77},{"year":2002,"month":1,"value":-3.47},{"year":2002,"month":2,"value":0.93},{"year":2002,"month":3,"value":9.31},{"year":2002,"month":4,"value":16.35},{"year":2002,"month":5,"value":24.71},{"year":2002,"month":6,"value":27.72},{"year":2002,"month":7,"value":27.52},{"year":2002,"month":8,"value":26.03},{"year":2002,"month":9,"value":18.69},{"year":2002,"month":10,"value":10.95},{"year":2002,"month":11,"value":6.54},{"year":2002,"month":12,"value":0},{"year":2003,"month":1,"value":1.8},{"year":2003,"month":2,"value":3.44},{"year":2003,"month":3,"value":9.54},{"year":2003,"month":4,"value":12.75},{"year":2003,"month":5,"value":19.07},{"year":2003,"month":6,"value":24.97},{"year":2003,"month":7,"value":28.66},{"year":2003,"month":8,"value":27.22},{"year":2003,"month":9,"value":21.3},{"year":2003,"month":10,"value":14.18},{"year":2003,"month":11,"value":6.33},{"year":2003,"month":12,"value":-5.87},{"year":2004,"month":1,"value":-0.32},{"year":2004,"month":2,"value":-0.1},{"year":2004,"month":3,"value":3.79},{"year":2004,"month":4,"value":12.04},{"year":2004,"month":5,"value":19.02},{"year":2004,"month":6,"value":24.22},{"year":2004,"month":7,"value":28},{"year":2004,"month":8,"value":27.59},{"year":2004,"month":9,"value":20.36},{"year":2004,"month":10,"value":14.33},{"year":2004,"month":11,"value":5.31},{"year":2004,"month":12,"value":-0.13},{"year":2005,"month":1,"value":1.43},{"year":2005,"month":2,"value":4.38},{"year":2005,"month":3,"value":8.54},{"year":2005,"month":4,"value":13.25},{"year":2005,"month":5,"value":22.33},{"year":2005,"month":6,"value":27.45},{"year":2005,"month":7,"value":27.42},{"year":2005,"month":8,"value":26.44},{"year":2005,"month":9,"value":20.97},{"year":2005,"month":10,"value":11.4},{"year":2005,"month":11,"value":7.76},{"year":2005,"month":12,"value":0.02},{"year":2006,"month":1,"value":-2.17},{"year":2006,"month":2,"value":-3.87},{"year":2006,"month":3,"value":9.37},{"year":2006,"month":4,"value":15.48},{"year":2006,"month":5,"value":22.21},{"year":2006,"month":6,"value":27.84},{"year":2006,"month":7,"value":29.83},{"year":2006,"month":8,"value":25.93},{"year":2006,"month":9,"value":22.56},{"year":2006,"month":10,"value":13.31},{"year":2006,"month":11,"value":5.28},{"year":2006,"month":12,"value":1.55},{"year":2007,"month":1,"value":-8.8},{"year":2007,"month":2,"value":3.35},{"year":2007,"month":3,"value":8.55},{"year":2007,"month":4,"value":15.76},{"year":2007,"month":5,"value":22.51},{"year":2007,"month":6,"value":28.05},{"year":2007,"month":7,"value":27.7},{"year":2007,"month":8,"value":28.36},{"year":2007,"month":9,"value":19.72},{"year":2007,"month":10,"value":14.5},{"year":2007,"month":11,"value":5.49},{"year":2007,"month":12,"value":-1.72},{"year":2008,"month":1,"value":0.89},{"year":2008,"month":2,"value":1.97},{"year":2008,"month":3,"value":5.78},{"year":2008,"month":4,"value":16.39},{"year":2008,"month":5,"value":22.11},{"year":2008,"month":6,"value":27.21},{"year":2008,"month":7,"value":28.72},{"year":2008,"month":8,"value":27.41},{"year":2008,"month":9,"value":20.72},{"year":2008,"month":10,"value":11.39},{"year":2008,"month":11,"value":5.74},{"year":2008,"month":12,"value":-1.78},{"year":2009,"month":1,"value":-12.79},{"year":2009,"month":2,"value":-3.48},{"year":2009,"month":3,"value":12.74},{"year":2009,"month":4,"value":16.63},{"year":2009,"month":5,"value":23.43},{"year":2009,"month":6,"value":27.44},{"year":2009,"month":7,"value":29.7},{"year":2009,"month":8,"value":27.82},{"year":2009,"month":9,"value":19.3},{"year":2009,"month":10,"value":12.59},{"year":2009,"month":11,"value":5.67},{"year":2009,"month":12,"value":-0.68},{"year":2010,"month":1,"value":-1.64},{"year":2010,"month":2,"value":2.53},{"year":2010,"month":3,"value":8.86},{"year":2010,"month":4,"value":11.47},{"year":2010,"month":5,"value":21.45},{"year":2010,"month":6,"value":26.38},{"year":2010,"month":7,"value":28.61},{"year":2010,"month":8,"value":25.9},{"year":2010,"month":9,"value":20.08},{"year":2010,"month":10,"value":12.91},{"year":2010,"month":11,"value":5.52},{"year":2010,"month":12,"value":0.9},{"year":2011,"month":1,"value":-0.79},{"year":2011,"month":2,"value":-2.84},{"year":2011,"month":3,"value":8.17},{"year":2011,"month":4,"value":15.74},{"year":2011,"month":5,"value":21.87},{"year":2011,"month":6,"value":28.29},{"year":2011,"month":7,"value":28.97},{"year":2011,"month":8,"value":27.84},{"year":2011,"month":9,"value":20.16},{"year":2011,"month":10,"value":14.21},{"year":2011,"month":11,"value":7.28},{"year":2011,"month":12,"value":1.35},{"year":2012,"month":1,"value":-3.18},{"year":2012,"month":2,"value":-2.41},{"year":2012,"month":3,"value":6.16},{"year":2012,"month":4,"value":16},{"year":2012,"month":5,"value":23.36},{"year":2012,"month":6,"value":27.67},{"year":2012,"month":7,"value":29.27},{"year":2012,"month":8,"value":27.55},{"year":2012,"month":9,"value":20.76},{"year":2012,"month":10,"value":13.04},{"year":2012,"month":11,"value":1.74},{"year":2012,"month":12,"value":-3.62},{"year":2013,"month":1,"value":-4.5},{"year":2013,"month":2,"value":-5.73},{"year":2013,"month":3,"value":5.07},{"year":2013,"month":4,"value":19.62},{"year":2013,"month":5,"value":22.97},{"year":2013,"month":6,"value":27.92},{"year":2013,"month":7,"value":29.6},{"year":2013,"month":8,"value":28.28},{"year":2013,"month":9,"value":19.98},{"year":2013,"month":10,"value":13.96},{"year":2013,"month":11,"value":4.59},{"year":2013,"month":12,"value":-4.07},{"year":2014,"month":1,"value":0.04},{"year":2014,"month":2,"value":2.08},{"year":2014,"month":3,"value":9.23},{"year":2014,"month":4,"value":14.63},{"year":2014,"month":5,"value":22.5},{"year":2014,"month":6,"value":27.23},{"year":2014,"month":7,"value":29.19},{"year":2014,"month":8,"value":26.05},{"year":2014,"month":9,"value":22.39},{"year":2014,"month":10,"value":12.52},{"year":2014,"month":11,"value":6.72},{"year":2014,"month":12,"value":-0.14},{"year":2015,"month":1,"value":-2.69},{"year":2015,"month":2,"value":-6.77},{"year":2015,"month":3,"value":7.08},{"year":2015,"month":4,"value":12.6},{"year":2015,"month":5,"value":24.54},{"year":2015,"month":6,"value":28.66},{"year":2015,"month":7,"value":27.53},{"year":2015,"month":8,"value":28.64},{"year":2015,"month":9,"value":20.47},{"year":2015,"month":10,"value":10.19},{"year":2015,"month":11,"value":1.78},{"year":2015,"month":12,"value":-0.6},{"year":2016,"month":1,"value":-1.06},{"year":2016,"month":2,"value":2.23},{"year":2016,"month":3,"value":5.39},{"year":2016,"month":4,"value":15.48},{"year":2016,"month":5,"value":22.28},{"year":2016,"month":6,"value":29.1},{"year":2016,"month":7,"value":30.04},{"year":2016,"month":8,"value":26.34},{"year":2016,"month":9,"value":20.4},{"year":2016,"month":10,"value":11.56},{"year":2016,"month":11,"value":4.59},{"year":2016,"month":12,"value":2.51},{"year":2017,"month":1,"value":2.38},{"year":2017,"month":2,"value":4.59},{"year":2017,"month":3,"value":10.81},{"year":2017,"month":4,"value":15.3},{"year":2017,"month":5,"value":22.59},{"year":2017,"month":6,"value":27.43},{"year":2017,"month":7,"value":29.28},{"year":2017,"month":8,"value":27.81},{"year":2017,"month":9,"value":21.96},{"year":2017,"month":10,"value":9.82},{"year":2017,"month":11,"value":1.69},{"year":2017,"month":12,"value":0.77},{"year":2018,"month":1,"value":-0.65},{"year":2018,"month":2,"value":-1.62},{"year":2018,"month":3,"value":5.94},{"year":2018,"month":4,"value":14.22},{"year":2018,"month":5,"value":23.21},{"year":2018,"month":6,"value":27.03},{"year":2018,"month":7,"value":30.12},{"year":2018,"month":8,"value":27.13},{"year":2018,"month":9,"value":21.24},{"year":2018,"month":10,"value":12.71},{"year":2018,"month":11,"value":7.04},{"year":2018,"month":12,"value":-1.89},{"year":2019,"month":1,"value":-2.43},{"year":2019,"month":2,"value":-0.5},{"year":2019,"month":3,"value":9.22},{"year":2019,"month":4,"value":14.46},{"year":2019,"month":5,"value":21.4},{"year":2019,"month":6,"value":26.61},{"year":2019,"month":7,"value":31.39},{"year":2019,"month":8,"value":26.15},{"year":2019,"month":9,"value":20.02},{"year":2019,"month":10,"value":12.43},{"year":2019,"month":11,"value":2.69},{"year":2019,"month":12,"value":-0.01},{"year":2020,"month":1,"value":1.93},{"year":2020,"month":2,"value":1.79},{"year":2020,"month":3,"value":9.65},{"year":2020,"month":4,"value":14.51},{"year":2020,"month":5,"value":22.86},{"year":2020,"month":6,"value":27.27},{"year":2020,"month":7,"value":31.44},{"year":2020,"month":8,"value":26.15},{"year":2020,"month":9,"value":19.97},{"year":2020,"month":10,"value":13.93},{"year":2020,"month":11,"value":1.53},{"year":2020,"month":12,"value":2.41},{"year":2021,"month":1,"value":0.1},{"year":2021,"month":2,"value":4.2},{"year":2021,"month":3,"value":9.29},{"year":2021,"month":4,"value":15.06},{"year":2021,"month":5,"value":23.07},{"year":2021,"month":6,"value":27.7},{"year":2021,"month":7,"value":29.6},{"year":2021,"month":8,"value":26.06},{"year":2021,"month":9,"value":18.74},{"year":2021,"month":10,"value":11.1},{"year":2021,"month":11,"value":1.8},{"year":2021,"month":12,"value":-5.14},{"year":2022,"month":1,"value":-1.66},{"year":2022,"month":2,"value":3.48},{"year":2022,"month":3,"value":5.94},{"year":2022,"month":4,"value":16.62},{"year":2022,"month":5,"value":25.14},{"year":2022,"month":6,"value":29.15},{"year":2022,"month":7,"value":30.57},{"year":2022,"month":8,"value":28.24},{"year":2022,"month":9,"value":21.05},{"year":2022,"month":10,"value":9.77},{"year":2022,"month":11,"value":3.24},{"year":2022,"month":12,"value":2.22},{"year":2023,"month":1,"value":0.15},{"year":2023,"month":2,"value":3.96},{"year":2023,"month":3,"value":6.35},{"year":2023,"month":4,"value":19.26},{"year":2023,"month":5,"value":21.73},{"year":2023,"month":6,"value":28.53},{"year":2023,"month":7,"value":29.75},{"year":2023,"month":8,"value":26.34},{"year":2023,"month":9,"value":22.02},{"year":2023,"month":10,"value":12.83},{"year":2023,"month":11,"value":5.74},{"year":2023,"month":12,"value":-3.83},{"year":2024,"month":1,"value":-4.73},{"year":2024,"month":2,"value":2.42},{"year":2024,"month":3,"value":12.9},{"year":2024,"month":4,"value":16.87},{"year":2024,"month":5,"value":22.62},{"year":2024,"month":6,"value":28.8},{"year":2024,"month":7,"value":30.9},{"year":2024,"month":8,"value":27.36},{"year":2024,"month":9,"value":20.22},{"year":2024,"month":10,"value":14.27},{"year":2024,"month":11,"value":10.14},{"year":2024,"month":12,"value":1.46},{"year":2025,"month":1,"value":0.42},{"year":2025,"month":2,"value":1.3},{"year":2025,"month":3,"value":7.74},{"year":2025,"month":4,"value":17.63},{"year":2025,"month":5,"value":20.78},{"year":2025,"month":6,"value":29.2},{"year":2025,"month":7,"value":29.33},{"year":2025,"month":8,"value":27.92},{"year":2025,"month":9,"value":19.85},{"year":2025,"month":10,"value":13.11},{"year":2025,"month":11,"value":6.37},{"year":2025,"month":12,"value":-1.12},{"year":2026,"month":1,"value":-0.11},{"year":2026,"month":2,"value":0.61},{"year":2026,"month":3,"value":8.95}],"precipYearly":[{"year":1940,"value":151.6},{"year":1941,"value":133.7},{"year":1942,"value":150.9},{"year":1943,"value":197.2},{"year":1944,"value":161.6},{"year":1945,"value":196.7},{"year":1946,"value":125.4},{"year":1947,"value":125.6},{"year":1948,"value":190.9},{"year":1949,"value":258.8,"rollingAvg":169.2},{"year":1950,"value":175.1,"rollingAvg":171.6},{"year":1951,"value":222.5,"rollingAvg":180.5},{"year":1952,"value":259.7,"rollingAvg":191.4},{"year":1953,"value":323.7,"rollingAvg":204},{"year":1954,"value":278.9,"rollingAvg":215.7},{"year":1955,"value":217,"rollingAvg":217.8},{"year":1956,"value":237.3,"rollingAvg":229},{"year":1957,"value":236.9,"rollingAvg":240.1},{"year":1958,"value":275,"rollingAvg":248.5},{"year":1959,"value":239.2,"rollingAvg":246.5},{"year":1960,"value":211.5,"rollingAvg":250.2},{"year":1961,"value":207.3,"rollingAvg":248.7},{"year":1962,"value":215.9,"rollingAvg":244.3},{"year":1963,"value":266.7,"rollingAvg":238.6},{"year":1964,"value":274.3,"rollingAvg":238.1},{"year":1965,"value":223.9,"rollingAvg":238.8},{"year":1966,"value":198.4,"rollingAvg":234.9},{"year":1967,"value":267,"rollingAvg":237.9},{"year":1968,"value":243.8,"rollingAvg":234.8},{"year":1969,"value":393.3,"rollingAvg":250.2},{"year":1970,"value":213.7,"rollingAvg":250.4},{"year":1971,"value":178.2,"rollingAvg":247.5},{"year":1972,"value":255.5,"rollingAvg":251.5},{"year":1973,"value":251.5,"rollingAvg":250},{"year":1974,"value":196.8,"rollingAvg":242.2},{"year":1975,"value":188.1,"rollingAvg":238.6},{"year":1976,"value":256,"rollingAvg":244.4},{"year":1977,"value":227.6,"rollingAvg":240.4},{"year":1978,"value":307.5,"rollingAvg":246.8},{"year":1979,"value":266.3,"rollingAvg":234.1},{"year":1980,"value":268.7,"rollingAvg":239.6},{"year":1981,"value":329.2,"rollingAvg":254.7},{"year":1982,"value":229.4,"rollingAvg":252.1},{"year":1983,"value":223.3,"rollingAvg":249.3},{"year":1984,"value":234,"rollingAvg":253},{"year":1985,"value":239.9,"rollingAvg":258.2},{"year":1986,"value":213,"rollingAvg":253.9},{"year":1987,"value":291.6,"rollingAvg":260.3},{"year":1988,"value":280.4,"rollingAvg":257.6},{"year":1989,"value":226.4,"rollingAvg":253.6},{"year":1990,"value":257.2,"rollingAvg":252.4},{"year":1991,"value":290.8,"rollingAvg":248.6},{"year":1992,"value":283.3,"rollingAvg":254},{"year":1993,"value":310.3,"rollingAvg":262.7},{"year":1994,"value":258.8,"rollingAvg":265.2},{"year":1995,"value":186.8,"rollingAvg":259.9},{"year":1996,"value":190.8,"rollingAvg":257.6},{"year":1997,"value":265.8,"rollingAvg":255.1},{"year":1998,"value":315.7,"rollingAvg":258.6},{"year":1999,"value":252.1,"rollingAvg":261.2},{"year":2000,"value":181.6,"rollingAvg":253.6},{"year":2001,"value":194.1,"rollingAvg":243.9},{"year":2002,"value":321.3,"rollingAvg":247.7},{"year":2003,"value":351.4,"rollingAvg":251.8},{"year":2004,"value":269.7,"rollingAvg":252.9},{"year":2005,"value":244.1,"rollingAvg":258.7},{"year":2006,"value":227.3,"rollingAvg":262.3},{"year":2007,"value":225.4,"rollingAvg":258.3},{"year":2008,"value":178.9,"rollingAvg":244.6},{"year":2009,"value":280.7,"rollingAvg":247.5},{"year":2010,"value":221,"rollingAvg":251.4},{"year":2011,"value":219.6,"rollingAvg":253.9},{"year":2012,"value":216.9,"rollingAvg":243.5},{"year":2013,"value":226.1,"rollingAvg":231},{"year":2014,"value":223.8,"rollingAvg":226.4},{"year":2015,"value":289.3,"rollingAvg":230.9},{"year":2016,"value":277.3,"rollingAvg":235.9},{"year":2017,"value":227.1,"rollingAvg":236.1},{"year":2018,"value":212,"rollingAvg":239.4},{"year":2019,"value":257.5,"rollingAvg":237.1},{"year":2020,"value":217.2,"rollingAvg":236.7},{"year":2021,"value":159.2,"rollingAvg":230.6},{"year":2022,"value":236.7,"rollingAvg":232.6},{"year":2023,"value":187.7,"rollingAvg":228.8},{"year":2024,"value":265.4,"rollingAvg":232.9}],"precipMonthly":{"source":"World Bank CKP (CRU TS 4.08)","sourceUrl":"https://climateknowledgeportal.worldbank.org/","units":"mm","yearRange":[1901,2023],"yearly":[{"year":1901,"value":191.9},{"year":1902,"value":226},{"year":1903,"value":191},{"year":1904,"value":182.1},{"year":1905,"value":178.3},{"year":1906,"value":209.4},{"year":1907,"value":230.4},{"year":1908,"value":205.1},{"year":1909,"value":153.3},{"year":1910,"value":162.7,"rollingAvg":193.02},{"year":1911,"value":212.9,"rollingAvg":195.12},{"year":1912,"value":172.8,"rollingAvg":189.8},{"year":1913,"value":194.1,"rollingAvg":190.11},{"year":1914,"value":212.4,"rollingAvg":193.14},{"year":1915,"value":170.2,"rollingAvg":192.33},{"year":1916,"value":169.2,"rollingAvg":188.31},{"year":1917,"value":87.3,"rollingAvg":174},{"year":1918,"value":182.9,"rollingAvg":171.78},{"year":1919,"value":189,"rollingAvg":175.35},{"year":1920,"value":221.6,"rollingAvg":181.24},{"year":1921,"value":211.5,"rollingAvg":181.1},{"year":1922,"value":196.9,"rollingAvg":183.51},{"year":1923,"value":224,"rollingAvg":186.5},{"year":1924,"value":228.9,"rollingAvg":188.15},{"year":1925,"value":151.6,"rollingAvg":186.29},{"year":1926,"value":198.8,"rollingAvg":189.25},{"year":1927,"value":145,"rollingAvg":195.02},{"year":1928,"value":190.6,"rollingAvg":195.79},{"year":1929,"value":161.5,"rollingAvg":193.04},{"year":1930,"value":171.7,"rollingAvg":188.05},{"year":1931,"value":229.3,"rollingAvg":189.83},{"year":1932,"value":192.6,"rollingAvg":189.4},{"year":1933,"value":219.4,"rollingAvg":188.94},{"year":1934,"value":226.7,"rollingAvg":188.72},{"year":1935,"value":178.2,"rollingAvg":191.38},{"year":1936,"value":155.2,"rollingAvg":187.02},{"year":1937,"value":166.1,"rollingAvg":189.13},{"year":1938,"value":184.1,"rollingAvg":188.48},{"year":1939,"value":195.2,"rollingAvg":191.85},{"year":1940,"value":214.2,"rollingAvg":196.1},{"year":1941,"value":214.5,"rollingAvg":194.62},{"year":1942,"value":207.8,"rollingAvg":196.14},{"year":1943,"value":216.1,"rollingAvg":195.81},{"year":1944,"value":125.3,"rollingAvg":185.67},{"year":1945,"value":230.1,"rollingAvg":190.86},{"year":1946,"value":144.6,"rollingAvg":189.8},{"year":1947,"value":175.8,"rollingAvg":190.77},{"year":1948,"value":176.4,"rollingAvg":190},{"year":1949,"value":223.2,"rollingAvg":192.8},{"year":1950,"value":142,"rollingAvg":185.58},{"year":1951,"value":190.9,"rollingAvg":183.22},{"year":1952,"value":235.3,"rollingAvg":185.97},{"year":1953,"value":263.9,"rollingAvg":190.75},{"year":1954,"value":188.7,"rollingAvg":197.09},{"year":1955,"value":165.4,"rollingAvg":190.62},{"year":1956,"value":181.2,"rollingAvg":194.28},{"year":1957,"value":181.9,"rollingAvg":194.89},{"year":1958,"value":238.4,"rollingAvg":201.09},{"year":1959,"value":196.9,"rollingAvg":198.46},{"year":1960,"value":190.9,"rollingAvg":203.35},{"year":1961,"value":156.3,"rollingAvg":199.89},{"year":1962,"value":192.8,"rollingAvg":195.64},{"year":1963,"value":227.2,"rollingAvg":191.97},{"year":1964,"value":216.2,"rollingAvg":194.72},{"year":1965,"value":173.3,"rollingAvg":195.51},{"year":1966,"value":181.2,"rollingAvg":195.51},{"year":1967,"value":222.4,"rollingAvg":199.56},{"year":1968,"value":210,"rollingAvg":196.72},{"year":1969,"value":354.2,"rollingAvg":212.45},{"year":1970,"value":165.3,"rollingAvg":209.89},{"year":1971,"value":127.6,"rollingAvg":207.02},{"year":1972,"value":208.3,"rollingAvg":208.57},{"year":1973,"value":210.4,"rollingAvg":206.89},{"year":1974,"value":167.9,"rollingAvg":202.06},{"year":1975,"value":137.8,"rollingAvg":198.51},{"year":1976,"value":208.8,"rollingAvg":201.27},{"year":1977,"value":200.2,"rollingAvg":199.05},{"year":1978,"value":259.9,"rollingAvg":204.04},{"year":1979,"value":210.9,"rollingAvg":189.71},{"year":1980,"value":218.3,"rollingAvg":195.01},{"year":1981,"value":269.9,"rollingAvg":209.24},{"year":1982,"value":203.2,"rollingAvg":208.73},{"year":1983,"value":178.7,"rollingAvg":205.56},{"year":1984,"value":190.3,"rollingAvg":207.8},{"year":1985,"value":184.9,"rollingAvg":212.51},{"year":1986,"value":162.3,"rollingAvg":207.86},{"year":1987,"value":253.6,"rollingAvg":213.2},{"year":1988,"value":216.4,"rollingAvg":208.85},{"year":1989,"value":181.4,"rollingAvg":205.9},{"year":1990,"value":206.3,"rollingAvg":204.7},{"year":1991,"value":235.6,"rollingAvg":201.27},{"year":1992,"value":245,"rollingAvg":205.45},{"year":1993,"value":271.5,"rollingAvg":214.73},{"year":1994,"value":227.6,"rollingAvg":218.46},{"year":1995,"value":136.6,"rollingAvg":213.63},{"year":1996,"value":144.4,"rollingAvg":211.84},{"year":1997,"value":213.8,"rollingAvg":207.86},{"year":1998,"value":265.1,"rollingAvg":212.73},{"year":1999,"value":210.6,"rollingAvg":215.65},{"year":2000,"value":164.6,"rollingAvg":211.48},{"year":2001,"value":172.6,"rollingAvg":205.18},{"year":2002,"value":255.3,"rollingAvg":206.21},{"year":2003,"value":286.6,"rollingAvg":207.72},{"year":2004,"value":236.2,"rollingAvg":208.58},{"year":2005,"value":207.9,"rollingAvg":215.71},{"year":2006,"value":202.8,"rollingAvg":221.55},{"year":2007,"value":194.9,"rollingAvg":219.66},{"year":2008,"value":162.2,"rollingAvg":209.37},{"year":2009,"value":236.5,"rollingAvg":211.96},{"year":2010,"value":180.9,"rollingAvg":213.59},{"year":2011,"value":203.1,"rollingAvg":216.64},{"year":2012,"value":195.9,"rollingAvg":210.7},{"year":2013,"value":220.8,"rollingAvg":204.12},{"year":2014,"value":217,"rollingAvg":202.2},{"year":2015,"value":250.1,"rollingAvg":206.42},{"year":2016,"value":259.5,"rollingAvg":212.09},{"year":2017,"value":202.4,"rollingAvg":212.84},{"year":2018,"value":178.5,"rollingAvg":214.47},{"year":2019,"value":223.8,"rollingAvg":213.2},{"year":2020,"value":196.8,"rollingAvg":214.79},{"year":2021,"value":136.7,"rollingAvg":208.15},{"year":2022,"value":228.3,"rollingAvg":211.39},{"year":2023,"value":171.2,"rollingAvg":206.43}],"monthlyComparison":[{"monthLabel":"Jan 2023","month":1,"year":2023,"recent":14.1,"historicAvg":22.1,"diff":-8},{"monthLabel":"Feb 2023","month":2,"year":2023,"recent":30.8,"historicAvg":20.99,"diff":9.81},{"monthLabel":"Mar 2023","month":3,"year":2023,"recent":13.7,"historicAvg":34.62,"diff":-20.92},{"monthLabel":"Apr 2023","month":4,"year":2023,"recent":20.1,"historicAvg":34.57,"diff":-14.47},{"monthLabel":"May 2023","month":5,"year":2023,"recent":16.2,"historicAvg":20.28,"diff":-4.08},{"monthLabel":"Jun 2023","month":6,"year":2023,"recent":7.5,"historicAvg":6.62,"diff":0.88},{"monthLabel":"Jul 2023","month":7,"year":2023,"recent":2.9,"historicAvg":4.28,"diff":-1.38},{"monthLabel":"Aug 2023","month":8,"year":2023,"recent":6.1,"historicAvg":2.03,"diff":4.07},{"monthLabel":"Sep 2023","month":9,"year":2023,"recent":3,"historicAvg":3.11,"diff":-0.11},{"monthLabel":"Oct 2023","month":10,"year":2023,"recent":22.8,"historicAvg":13.37,"diff":9.43},{"monthLabel":"Nov 2023","month":11,"year":2023,"recent":17.3,"historicAvg":18.02,"diff":-0.72},{"monthLabel":"Dec 2023","month":12,"year":2023,"recent":16.7,"historicAvg":23.2,"diff":-6.5}],"latestMonthStats":{"label":"Dec 2023","value":16.7,"diff":-6.5,"rank":81,"total":123,"recordLabel":"Dec 1933","recordValue":48.6},"latestThreeMonthStats":{"label":"Oct–Dec 2023","value":18.93,"diff":0.73,"rank":41,"total":123,"recordLabel":"Oct–Dec 1953","recordValue":34.73}},"dataPoints":1023,"dateRange":"1941-01 to 2026-03","lastUpdated":"2026-04-v8","generatedAt":"2026-04-24T10:01:16.554Z"}